Workbook

Sheet Dashboard
A1: PIQUINZADA 2027 | DASHBOARD EXECUTIVO PMO
A2: Atualizado automaticamente a partir de ENTRADAS PMO, VENDAS, PATROCINIOS e CUSTOS.
A4: CENÁRIO CONSERVADOR | D4: CENÁRIO BASE | G4: CENÁRIO AGRESSIVO
A5: Receita total | B5: =Cenarios!$J$10 -> 195458 | D5: Receita total | E5: =Cenarios!$J$11 -> 491026.5 | G5: Receita total | H5: =Cenarios!$J$12 -> 689420
A6: ↳ Receita de ingressos | B6: =Cenarios!$F$10 -> 113758 | D6: ↳ Receita de ingressos | E6: =Cenarios!$F$11 -> 278520.8 | G6: ↳ Receita de ingressos | H6: =Cenarios!$F$12 -> 321770
A7: ↳ Receita de patrocínio | B7: =Cenarios!$H$10 -> 47820 | D7: ↳ Receita de patrocínio | E7: =Cenarios!$H$11 -> 127000 | G7: ↳ Receita de patrocínio | H7: =Cenarios!$H$12 -> 257400
A8: ↳ Receita de consumo/ativações | B8: =Cenarios!$G$10 -> 33880 | D8: ↳ Receita de consumo/ativações | E8: =Cenarios!$G$11 -> 85505.7 | G8: ↳ Receita de consumo/ativações | H8: =Cenarios!$G$12 -> 110250
A9: Custo total | B9: =Cenarios!$K$10 -> 403049.8 | D9: Custo total | E9: =Cenarios!$K$11 -> 475795.43 | G9: Custo total | H9: =Cenarios!$K$12 -> 571042.67
A10: RESULTADO (lucro/prejuízo) | B10: =Cenarios!$L$10 -> -207591.8 | D10: RESULTADO (lucro/prejuízo) | E10: =Cenarios!$L$11 -> 15231.069 | G10: RESULTADO (lucro/prejuízo) | H10: =Cenarios!$L$12 -> 118377.33
A11: Margem líquida | B11: =Cenarios!$M$10 -> -1.0620788 | D11: Margem líquida | E11: =Cenarios!$M$11 -> 0.031018833 | G11: Margem líquida | H11: =Cenarios!$M$12 -> 0.17170568
A12: Quantidade de pagantes | B12: =Cenarios!$B$10 -> 1540 | D12: Quantidade de pagantes | E12: =Cenarios!$B$11 -> 2850 | G12: Quantidade de pagantes | H12: =Cenarios!$B$12 -> 3150
A13: Capacidade utilizada | B13: =Cenarios!$D$10 -> 0.75454545 | D13: Capacidade utilizada | E13: =Cenarios!$D$11 -> 1 | G13: Capacidade utilizada | H13: =Cenarios!$D$12 -> 0.95142857
A14: Ticket médio | B14: =Cenarios!$E$10 -> 80.292208 | D14: Ticket médio | E14: =Cenarios!$E$11 -> 106.22456 | G14: Ticket médio | H14: =Cenarios!$E$12 -> 111.03175
A15: Ponto de equilíbrio (pagantes) | B15: =Cenarios!$R$10 -> 3705.3733 | D15: Ponto de equilíbrio (pagantes) | E15: =Cenarios!$R$11 -> 2730.7544 | G15: Ponto de equilíbrio (pagantes) | H15: =Cenarios!$R$12 -> 2286.8719
A16: % capacidade necessário p/ break-even | B16: =Cenarios!$S$10 -> 1.6842606 | D16: % capacidade necessário p/ break-even | E16: =Cenarios!$S$11 -> 0.91025148 | G16: % capacidade necessário p/ break-even | H16: =Cenarios!$S$12 -> 0.65339198
A17: Receita por participante | B17: =Cenarios!$N$10 -> 126.92078 | D17: Receita por participante | E17: =Cenarios!$N$11 -> 172.29 | G17: Receita por participante | H17: =Cenarios!$N$12 -> 218.86349
A18: Custo por participante | B18: =Cenarios!$O$10 -> 261.72065 | D18: Custo por participante | E18: =Cenarios!$O$11 -> 166.94577 | G18: Custo por participante | H18: =Cenarios!$O$12 -> 181.28339
A19: Patrocínio necessário (mín. p/ cachê) | B19: =Cenarios!$U$10 -> 160000 | D19: Patrocínio necessário (mín. p/ cachê) | E19: =Cenarios!$U$11 -> 180000 | G19: Patrocínio necessário (mín. p/ cachê) | H19: =Cenarios!$U$12 -> 200000
A20: Patrocínio já considerado no cenário | B20: =Cenarios!$H$10 -> 47820 | D20: Patrocínio já considerado no cenário | E20: =Cenarios!$H$11 -> 127000 | G20: Patrocínio já considerado no cenário | H20: =Cenarios!$H$12 -> 257400
A21: Cobertura do cachê pelo patrocínio | B21: =Cenarios!$H$10/'ENTRADAS PMO'!$C$39 -> 0.298875 | D21: Cobertura do cachê pelo patrocínio | E21: =Cenarios!$H$11/'ENTRADAS PMO'!$D$39 -> 0.70555556 | G21: Cobertura do cachê pelo patrocínio | H21: =Cenarios!$H$12/'ENTRADAS PMO'!$E$39 -> 1.287
A22: Margem de segurança financeira | B22: =Cenarios!$T$10 -> -1.4060865 | D22: Margem de segurança financeira | E22: =Cenarios!$T$11 -> 0.04184055 | G22: Margem de segurança financeira | H22: =Cenarios!$T$12 -> 0.27400891
A23: STATUS | B23: =Cenarios!$V$10 -> VERMELHO | D23: STATUS | E23: =Cenarios!$V$11 -> AMARELO | G23: STATUS | H23: =Cenarios!$V$12 -> VERDE
A24: CLASSIFICAÇÃO | B24: =Cenarios!$W$10 -> NO-GO | D24: CLASSIFICAÇÃO | E24: =Cenarios!$W$11 -> GO COM RESSALVAS | G24: CLASSIFICAÇÃO | H24: =Cenarios!$W$12 -> GO
A26: KPIs EXECUTIVOS (cenário Base / realizado)
A27: Receita projetada (Base) | B27: =Cenarios!$J$11 -> 491026.5 | D27: Receita contratada (patrocínio assinado) | E27: ='ENTRADAS PMO'!$D$22 -> 60000 | G27: Custo projetado (Base / BAC) | H27: =CUSTOS!$C$52 -> 475795.43
A28: Custo contratado | B28: =CUSTOS!$C$54 -> 0 | D28: Resultado projetado (Base) | E28: =Cenarios!$L$11 -> 15231.069 | G28: Margem (Base) | H28: =Cenarios!$M$11 -> 0.031018833
A29: Break-even (ingressos, Base) | B29: =Cenarios!$R$11 -> 2730.7544 | D29: Ingressos vendidos até hoje | E29: =VENDAS!$C$47 -> 0 | G29: Ingressos restantes (meta Base) | H29: =VENDAS!$C$52 -> 2850
A30: Ocupação (Base) | B30: =Cenarios!$D$11 -> 1 | D30: Ticket médio (Base) | E30: =Cenarios!$E$11 -> 106.22456 | G30: Patrocínio contratado | H30: ='ENTRADAS PMO'!$D$22 -> 60000
A31: Patrocínio pipeline | B31: ='ENTRADAS PMO'!$D$23 -> 160000 | D31: Cobertura de patrocínio (esperado/cachê) | E31: =Cenarios!$H$11/'ENTRADAS PMO'!$D$39 -> 0.70555556 | G31: Capital de giro necessário (Base) | H31: ='FLUXO DE CAIXA'!$B$65 -> 12483.96
A32: Contingência disponível | B32: =CUSTOS!F49-CUSTOS!H49 -> 35244.106 | D32: Exposição financeira (custo − patrocínio contratado) | E32: =CUSTOS!$C$52-'ENTRADAS PMO'!$D$22 -> 415795.43 | G32: Forecast final do resultado | H32: =CUSTOS!$C$55 -> 475795.43
A35: INDICADORES DE VENDA
A36: Data atual | B36: =VENDAS!$C$45 -> 46268 | D36: Data do evento | E36: =VENDAS!$C$46 -> 0 | G36: Dias restantes até o evento | H36: =VENDAS!$C$54 -> 0
A37: Ingressos vendidos | B37: =VENDAS!$C$47 -> 0 | D37: % vendido da capacidade Base | E37: =VENDAS!$C$49 -> 0 | G37: Gap para a meta (Base) | H37: =VENDAS!$C$52 -> 2850
A38: Velocidade média de vendas (ingressos/dia) | B38: =VENDAS!$C$55 -> 0 | D38: Venda diária necessária até o evento | E38: =VENDAS!$C$56 -> 0 | G38: Projeção de público final (ritmo atual) | H38: =VENDAS!$C$57 -> 0
A42: RECOMENDAÇÃO PMO (atualiza automaticamente)
A43: STATUS DO PROJETO | B43: =Cenarios!$W$11 -> GO COM RESSALVAS
A44: Resultado Base | B44: =Cenarios!$L$11 -> 15231.069
A45: Margem | B45: =Cenarios!$M$11 -> 0.031018833
A46: Break-even (ingressos) | B46: =Cenarios!$R$11 -> 2730.7544
A47: Patrocínio mínimo adicional necessário | B47: =MAX(0,Cenarios!$U$11-'ENTRADAS PMO'!$D$22) -> 120000
A48: Score de viabilidade | B48: ='SCORE VIABILIDADE'!$B$18 -> 32.941068
A49: Maior risco atual (maior score, não encerrado) | B49: =IFERROR(INDEX(RISCOS!$C$5:$C$20,MATCH(MAX(RISCOS!$O$5:$O$20),RISCOS!$O$5:$O$20,0)),"—") -> Não fechamento das cotas em negociação
A50: Ação prioritária | B50: =IF(Cenarios!$W$11="NO-GO","Revisar premissas comerciais e de custo do cenário Base antes de assumir novos compromissos financeiros",IF(RISCOS!$B$32>0,"Tratar os riscos críticos abertos na aba RISCOS antes do próximo Gate",IF('GATES PMO'!$D$6<'GATES PMO'!$C$6,"Avançar negociações de patrocínio antes de contratar definitivamente a atração principal (GATE 2)","Manter ritmo de vendas e patrocínio; revisar Dashboard semanalmente"))) -> Tratar os riscos críticos abertos na aba RISCOS antes do próximo Gate

Sheet ENTRADAS PMO
A1: PIQUINZADA 2027 | ENTRADAS PMO — PREMISSAS DOS 3 CENÁRIOS
A2: Fonte única de dados (Single Source of Truth). Preencha apenas as células AZUIS. As células CINZAS são calculadas automaticamente.
A4: Bloco | B4: Item | C4: CONSERVADOR | D4: BASE | E4: AGRESSIVO | F4: Observação / Unidade
A5: EVENTO
B6: Capacidade máxima do evento | C6: 2200 | D6: 3000 | E6: 3500 | F6: Público físico máximo suportado pelo espaço/estrutura
B7: Número de cortesias | C7: 120 | D7: 150 | E7: 180 | F7: Convidados, staff, imprensa, permutas (não pagantes)
B8: Ingressos vendidos (pagantes) | C8: =VENDAS!$C$12 -> 1540 | D8: =VENDAS!$C$25 -> 2850 | E8: =VENDAS!$C$38 -> 3150 | F8: Total vendido no plano de lotes (aba VENDAS)
B9: Público total (pagantes + cortesias) | C9: =C8+'ENTRADAS PMO'!$C$7 -> 1660 | D9: =D8+'ENTRADAS PMO'!$D$7 -> 3000 | E9: =E8+'ENTRADAS PMO'!$E$7 -> 3330
B10: % Ocupação da capacidade | C10: =C9/'ENTRADAS PMO'!$C$6 -> 0.75454545 | D10: =D9/'ENTRADAS PMO'!$D$6 -> 1 | E10: =E9/'ENTRADAS PMO'!$E$6 -> 0.95142857
A12: INGRESSOS (resumo — detalhe por lote na aba VENDAS)
B13: Taxa da plataforma de venda (%) | C13: 0.05 | D13: 0.05 | E13: 0.05 | F13: % sobre a receita bruta de ingressos
B14: Taxa de cartão / meios de pagamento (%) | C14: 0.03 | D14: 0.03 | E14: 0.03 | F14: % sobre a receita bruta de ingressos
B15: Tributos incidentes sobre ingressos (%) | C15: 0 | D15: 0 | E15: 0 | F15: Ajustar conforme regime tributário do evento
B16: Ticket médio realizado | C16: =VENDAS!$C$13 -> 80.292208 | D16: =VENDAS!$C$26 -> 106.22456 | E16: =VENDAS!$C$39 -> 111.03175
B17: Receita bruta de ingressos | C17: =VENDAS!$C$14 -> 123650 | D17: =VENDAS!$C$27 -> 302740 | E17: =VENDAS!$C$40 -> 349750
B18: Receita líquida de ingressos | C18: =VENDAS!$C$15 -> 113758 | D18: =VENDAS!$C$28 -> 278520.8 | E18: =VENDAS!$C$41 -> 321770
A20: PATROCÍNIOS (resumo — detalhe por cota na aba PATROCINIOS)
B21: Número de cotas comerciais | C21: =PATROCINIOS!$B$19 -> 10 | D21: =PATROCINIOS!$B$32 -> 12 | E21: =PATROCINIOS!$B$45 -> 16
B22: Patrocínio contratado (assinado) | C22: =PATROCINIOS!$B$20 -> 0 | D22: =PATROCINIOS!$B$33 -> 60000 | E22: =PATROCINIOS!$B$46 -> 198000
B23: Patrocínio em negociação/pipeline | C23: =PATROCINIOS!$B$21 -> 174200 | D23: =PATROCINIOS!$B$34 -> 160000 | E23: =PATROCINIOS!$B$47 -> 150000
B24: Patrocínio esperado (ponderado por probabilidade) | C24: =PATROCINIOS!$B$22 -> 47820 | D24: =PATROCINIOS!$B$35 -> 127000 | E24: =PATROCINIOS!$B$48 -> 257400
B25: Cobertura do cachê da atração pelo patrocínio esperado | C25: =C24/'ENTRADAS PMO'!$C$39 -> 0.298875 | D25: =D24/'ENTRADAS PMO'!$D$39 -> 0.70555556 | E25: =E24/'ENTRADAS PMO'!$E$39 -> 1.287
A27: CONSUMO / BAR / ATIVAÇÕES
B28: Consumo médio bruto por pessoa | C28: 55 | D28: 70 | E28: 80 | F28: Ticket médio de bar/ativações por participante
B29: Custo operacional do consumo (% da receita bruta) | C29: 0.6 | D29: 0.5714 | E29: 0.5625 | F29: Custo de mercadoria, equipe e operação do bar/ativações
B30: Margem líquida por pessoa | C30: ='ENTRADAS PMO'!$C$28*(1-'ENTRADAS PMO'!$C$29) -> 22 | D30: ='ENTRADAS PMO'!$D$28*(1-'ENTRADAS PMO'!$D$29) -> 30.002 | E30: ='ENTRADAS PMO'!$E$28*(1-'ENTRADAS PMO'!$E$29) -> 35
B31: Receita bruta de consumo/ativações | C31: ='ENTRADAS PMO'!$C$28*C8 -> 84700 | D31: ='ENTRADAS PMO'!$D$28*D8 -> 199500 | E31: ='ENTRADAS PMO'!$E$28*E8 -> 252000
B32: Custo operacional de consumo/ativações | C32: =C31*'ENTRADAS PMO'!$C$29 -> 50820 | D32: =D31*'ENTRADAS PMO'!$D$29 -> 113994.3 | E32: =E31*'ENTRADAS PMO'!$E$29 -> 141750
B33: Receita líquida de consumo/ativações | C33: =C30*C8 -> 33880 | D33: =D30*D8 -> 85505.7 | E33: =E30*E8 -> 110250
A35: OUTRAS RECEITAS
B36: Outras receitas (merchandising, permutas ativas, etc.) | C36: 0 | D36: 0 | E36: 0 | F36: Receitas não classificadas acima
A38: ATRAÇÕES
B39: Cachê atração principal | C39: 160000 | D39: 180000 | E39: 200000
B40: Cachês das atrações de apoio | C40: 8000 | D40: 10000 | E40: 14000
B41: DJs | C41: 6000 | D41: 7500 | E41: 10500
B42: Banda de abertura | C42: 4000 | D42: 5000 | E42: 7000
B43: Participações especiais | C43: 2000 | D43: 2500 | E43: 3500
B44: Subtotal Atrações | C44: =SUM(C39:C43) -> 180000 | D44: =SUM(D39:D43) -> 205000 | E44: =SUM(E39:E43) -> 235000
A46: ESTRUTURA
B47: Palco | C47: 22400 | D47: 25200 | E47: 30800
B48: Som | C48: 14400 | D48: 16200 | E48: 19800
B49: Iluminação | C49: 11200 | D49: 12600 | E49: 15400
B50: Painel de LED | C50: 9600 | D50: 10800 | E50: 13200
B51: Gerador | C51: 7200 | D51: 8100 | E51: 9900
B52: Banheiros químicos | C52: 4800 | D52: 5400 | E52: 6600
B53: Gradil / contenção | C53: 4000 | D53: 4500 | E53: 5500
B54: Tendas | C54: 3200 | D54: 3600 | E54: 4400
B55: Mobiliário | C55: 1600 | D55: 1800 | E55: 2200
B56: Estrutura de camarote | C56: 800 | D56: 900 | E56: 1100
B57: Decoração | C57: 800 | D57: 900 | E57: 1100
B58: Subtotal Estrutura | C58: =SUM(C47:C57) -> 80000 | D58: =SUM(D47:D57) -> 90000 | E58: =SUM(E47:E57) -> 110000
A60: OPERAÇÃO
B61: Segurança | C61: 12600 | D61: 14000 | E61: 16800
B62: Brigadistas | C62: 3150 | D62: 3500 | E62: 4200
B63: Bombeiro civil | C63: 2250 | D63: 2500 | E63: 3000
B64: Ambulância / SAMU privado | C64: 2250 | D64: 2500 | E64: 3000
B65: Limpeza | C65: 4050 | D65: 4500 | E65: 5400
B66: Recepção / credenciamento | C66: 2700 | D66: 3000 | E66: 3600
B67: Produção geral | C67: 9900 | D67: 11000 | E67: 13200
B68: Equipe de apoio | C68: 4050 | D68: 4500 | E68: 5400
B69: Licenças e alvarás | C69: 1800 | D69: 2000 | E69: 2400
B70: ECAD | C70: 1350 | D70: 1500 | E70: 1800
B71: Seguro do evento | C71: 900 | D71: 1000 | E71: 1200
B72: Subtotal Operação | C72: =SUM(C61:C71) -> 45000 | D72: =SUM(D61:D71) -> 50000 | E72: =SUM(E61:E71) -> 60000
A74: MARKETING
B75: Tráfego pago | C75: 8000 | D75: 11200 | E75: 14400
B76: Influenciadores | C76: 4000 | D76: 5600 | E76: 7200
B77: Designer | C77: 2500 | D77: 3500 | E77: 4500
B78: Fotografia | C78: 2500 | D78: 3500 | E78: 4500
B79: Filmagem | C79: 2500 | D79: 3500 | E79: 4500
B80: Assessoria de imprensa | C80: 2000 | D80: 2800 | E80: 3600
B81: Mídia (rádio/OOH) | C81: 2000 | D81: 2800 | E81: 3600
B82: Impressos | C82: 1000 | D82: 1400 | E82: 1800
B83: Comunicação visual | C83: 500 | D83: 700 | E83: 900
B84: Subtotal Marketing | C84: =SUM(C75:C83) -> 25000 | D84: =SUM(D75:D83) -> 35000 | E84: =SUM(E75:E83) -> 45000
A86: LOGÍSTICA
B87: Transporte | C87: 7000 | D87: 8400 | E87: 11200
B88: Passagens | C88: 3750 | D88: 4500 | E88: 6000
B89: Hospedagem | C89: 7500 | D89: 9000 | E89: 12000
B90: Alimentação | C90: 3000 | D90: 3600 | E90: 4800
B91: Camarim | C91: 2500 | D91: 3000 | E91: 4000
B92: Transfers | C92: 1250 | D92: 1500 | E92: 2000
B93: Subtotal Logística | C93: =SUM(C87:C92) -> 25000 | D93: =SUM(D87:D92) -> 30000 | E93: =SUM(E87:E92) -> 40000
A95: OUTROS
B96: Tributos sobre a receita total (%) | C96: 0.02 | D96: 0.015 | E96: 0.01
B97: Taxas bancárias (%) | C97: 0.02 | D97: 0.015 | E97: 0.01
B98: Comissões sobre vendas (%) | C98: 0.03 | D98: 0.02 | E98: 0.015
B99: Despesas administrativas | C99: 8000 | D99: 6000 | E99: 5000
B100: Reserva de contingência (%) | C100: 0.07 | D100: 0.08 | E100: 0.1 | F100: % sobre os custos diretos antes da contingência
A102: TOTAIS DE CUSTO
B103: Custos diretos (Atrações+Estrutura+Operação+Marketing+Logística+Administrativo) | C103: =C44+C58+C72+C84+C93+'ENTRADAS PMO'!$C$99 -> 363000 | D103: =D44+D58+D72+D84+D93+'ENTRADAS PMO'!$D$99 -> 416000 | E103: =E44+E58+E72+E84+E93+'ENTRADAS PMO'!$E$99 -> 495000
B104: Tributos + taxas bancárias + comissões (valor sobre a receita total) | C104: =('ENTRADAS PMO'!$C$96+'ENTRADAS PMO'!$C$97+'ENTRADAS PMO'!$C$98)*(C18+C24+C33+'ENTRADAS PMO'!$C$36) -> 13682.06 | D104: =('ENTRADAS PMO'!$D$96+'ENTRADAS PMO'!$D$97+'ENTRADAS PMO'!$D$98)*(D18+D24+D33+'ENTRADAS PMO'!$D$36) -> 24551.325 | E104: =('ENTRADAS PMO'!$E$96+'ENTRADAS PMO'!$E$97+'ENTRADAS PMO'!$E$98)*(E18+E24+E33+'ENTRADAS PMO'!$E$36) -> 24129.7
B105: Base de cálculo da contingência | C105: =C103+C104 -> 376682.06 | D105: =D103+D104 -> 440551.33 | E105: =E103+E104 -> 519129.7
B106: Contingência (valor) | C106: =C105*'ENTRADAS PMO'!$C$100 -> 26367.744 | D106: =D105*'ENTRADAS PMO'!$D$100 -> 35244.106 | E106: =E105*'ENTRADAS PMO'!$E$100 -> 51912.97
B107: CUSTO TOTAL DO CENÁRIO | C107: =C105+C106 -> 403049.8 | D107: =D105+D106 -> 475795.43 | E107: =E105+E106 -> 571042.67

Sheet VENDAS
A1: PIQUINZADA 2027 | VENDAS — PLANO DE LOTES E ACOMPANHAMENTO
A2: Fonte única dos dados de ingressos. Preencha a quantidade e o preço de cada lote em cada cenário.
A4: CENÁRIO CONSERVADOR
A5: Lote | B5: Preço (R$) | C5: Qtd. planejada | D5: % mix | E5: Receita bruta | F5: Taxa plataforma | G5: Taxa cartão | H5: Tributos | I5: Receita líquida | J5: Conversão acum. capacidade
A6: Pré-venda | B6: 60 | C6: 300 | D6: =C6/SUM($C$6:$C$10) -> 0.19480519 | E6: =B6*C6 -> 18000 | F6: =E6*'ENTRADAS PMO'!$C$13 -> 900 | G6: =E6*'ENTRADAS PMO'!$C$14 -> 540 | H6: =E6*'ENTRADAS PMO'!$C$15 -> 0 | I6: =E6-F6-G6-H6 -> 16560 | J6: =SUM($C$6:C6)/'ENTRADAS PMO'!$C$6 -> 0.13636364
A7: 1º lote | B7: 75 | C7: 550 | D7: =C7/SUM($C$6:$C$10) -> 0.35714286 | E7: =B7*C7 -> 41250 | F7: =E7*'ENTRADAS PMO'!$C$13 -> 2062.5 | G7: =E7*'ENTRADAS PMO'!$C$14 -> 1237.5 | H7: =E7*'ENTRADAS PMO'!$C$15 -> 0 | I7: =E7-F7-G7-H7 -> 37950 | J7: =SUM($C$6:C7)/'ENTRADAS PMO'!$C$6 -> 0.38636364
A8: 2º lote | B8: 90 | C8: 500 | D8: =C8/SUM($C$6:$C$10) -> 0.32467532 | E8: =B8*C8 -> 45000 | F8: =E8*'ENTRADAS PMO'!$C$13 -> 2250 | G8: =E8*'ENTRADAS PMO'!$C$14 -> 1350 | H8: =E8*'ENTRADAS PMO'!$C$15 -> 0 | I8: =E8-F8-G8-H8 -> 41400 | J8: =SUM($C$6:C8)/'ENTRADAS PMO'!$C$6 -> 0.61363636
A9: 3º lote | B9: 100 | C9: 150 | D9: =C9/SUM($C$6:$C$10) -> 0.097402597 | E9: =B9*C9 -> 15000 | F9: =E9*'ENTRADAS PMO'!$C$13 -> 750 | G9: =E9*'ENTRADAS PMO'!$C$14 -> 450 | H9: =E9*'ENTRADAS PMO'!$C$15 -> 0 | I9: =E9-F9-G9-H9 -> 13800 | J9: =SUM($C$6:C9)/'ENTRADAS PMO'!$C$6 -> 0.68181818
A10: Último lote | B10: 110 | C10: 40 | D10: =C10/SUM($C$6:$C$10) -> 0.025974026 | E10: =B10*C10 -> 4400 | F10: =E10*'ENTRADAS PMO'!$C$13 -> 220 | G10: =E10*'ENTRADAS PMO'!$C$14 -> 132 | H10: =E10*'ENTRADAS PMO'!$C$15 -> 0 | I10: =E10-F10-G10-H10 -> 4048 | J10: =SUM($C$6:C10)/'ENTRADAS PMO'!$C$6 -> 0.7
A12: Ingressos planejados (pagantes) | C12: =SUM(C6:C10) -> 1540
A13: Ticket médio planejado | C13: =SUM(E6:E10)/SUM(C6:C10) -> 80.292208
A14: Receita bruta planejada | C14: =SUM(E6:E10) -> 123650
A15: Receita líquida planejada | C15: =SUM(I6:I10) -> 113758
A17: CENÁRIO BASE
A18: Lote | B18: Preço (R$) | C18: Qtd. planejada | D18: % mix | E18: Receita bruta | F18: Taxa plataforma | G18: Taxa cartão | H18: Tributos | I18: Receita líquida | J18: Conversão acum. capacidade
A19: Pré-venda | B19: 70 | C19: 330 | D19: =C19/SUM($C$19:$C$23) -> 0.11578947 | E19: =B19*C19 -> 23100 | F19: =E19*'ENTRADAS PMO'!$D$13 -> 1155 | G19: =E19*'ENTRADAS PMO'!$D$14 -> 693 | H19: =E19*'ENTRADAS PMO'!$D$15 -> 0 | I19: =E19-F19-G19-H19 -> 21252 | J19: =SUM($C$19:C19)/'ENTRADAS PMO'!$D$6 -> 0.11
A20: 1º lote | B20: 85 | C20: 620 | D20: =C20/SUM($C$19:$C$23) -> 0.21754386 | E20: =B20*C20 -> 52700 | F20: =E20*'ENTRADAS PMO'!$D$13 -> 2635 | G20: =E20*'ENTRADAS PMO'!$D$14 -> 1581 | H20: =E20*'ENTRADAS PMO'!$D$15 -> 0 | I20: =E20-F20-G20-H20 -> 48484 | J20: =SUM($C$19:C20)/'ENTRADAS PMO'!$D$6 -> 0.31666667
A21: 2º lote | B21: 105 | C21: 800 | D21: =C21/SUM($C$19:$C$23) -> 0.28070175 | E21: =B21*C21 -> 84000 | F21: =E21*'ENTRADAS PMO'!$D$13 -> 4200 | G21: =E21*'ENTRADAS PMO'!$D$14 -> 2520 | H21: =E21*'ENTRADAS PMO'!$D$15 -> 0 | I21: =E21-F21-G21-H21 -> 77280 | J21: =SUM($C$19:C21)/'ENTRADAS PMO'!$D$6 -> 0.58333333
A22: 3º lote | B22: 122 | C22: 720 | D22: =C22/SUM($C$19:$C$23) -> 0.25263158 | E22: =B22*C22 -> 87840 | F22: =E22*'ENTRADAS PMO'!$D$13 -> 4392 | G22: =E22*'ENTRADAS PMO'!$D$14 -> 2635.2 | H22: =E22*'ENTRADAS PMO'!$D$15 -> 0 | I22: =E22-F22-G22-H22 -> 80812.8 | J22: =SUM($C$19:C22)/'ENTRADAS PMO'!$D$6 -> 0.82333333
A23: Último lote | B23: 145 | C23: 380 | D23: =C23/SUM($C$19:$C$23) -> 0.13333333 | E23: =B23*C23 -> 55100 | F23: =E23*'ENTRADAS PMO'!$D$13 -> 2755 | G23: =E23*'ENTRADAS PMO'!$D$14 -> 1653 | H23: =E23*'ENTRADAS PMO'!$D$15 -> 0 | I23: =E23-F23-G23-H23 -> 50692 | J23: =SUM($C$19:C23)/'ENTRADAS PMO'!$D$6 -> 0.95
A25: Ingressos planejados (pagantes) | C25: =SUM(C19:C23) -> 2850
A26: Ticket médio planejado | C26: =SUM(E19:E23)/SUM(C19:C23) -> 106.22456
A27: Receita bruta planejada | C27: =SUM(E19:E23) -> 302740
A28: Receita líquida planejada | C28: =SUM(I19:I23) -> 278520.8
A30: CENÁRIO AGRESSIVO
A31: Lote | B31: Preço (R$) | C31: Qtd. planejada | D31: % mix | E31: Receita bruta | F31: Taxa plataforma | G31: Taxa cartão | H31: Tributos | I31: Receita líquida | J31: Conversão acum. capacidade
A32: Pré-venda | B32: 80 | C32: 450 | D32: =C32/SUM($C$32:$C$36) -> 0.14285714 | E32: =B32*C32 -> 36000 | F32: =E32*'ENTRADAS PMO'!$E$13 -> 1800 | G32: =E32*'ENTRADAS PMO'!$E$14 -> 1080 | H32: =E32*'ENTRADAS PMO'!$E$15 -> 0 | I32: =E32-F32-G32-H32 -> 33120 | J32: =SUM($C$32:C32)/'ENTRADAS PMO'!$E$6 -> 0.12857143
A33: 1º lote | B33: 95 | C33: 800 | D33: =C33/SUM($C$32:$C$36) -> 0.25396825 | E33: =B33*C33 -> 76000 | F33: =E33*'ENTRADAS PMO'!$E$13 -> 3800 | G33: =E33*'ENTRADAS PMO'!$E$14 -> 2280 | H33: =E33*'ENTRADAS PMO'!$E$15 -> 0 | I33: =E33-F33-G33-H33 -> 69920 | J33: =SUM($C$32:C33)/'ENTRADAS PMO'!$E$6 -> 0.35714286
A34: 2º lote | B34: 115 | C34: 950 | D34: =C34/SUM($C$32:$C$36) -> 0.3015873 | E34: =B34*C34 -> 109250 | F34: =E34*'ENTRADAS PMO'!$E$13 -> 5462.5 | G34: =E34*'ENTRADAS PMO'!$E$14 -> 3277.5 | H34: =E34*'ENTRADAS PMO'!$E$15 -> 0 | I34: =E34-F34-G34-H34 -> 100510 | J34: =SUM($C$32:C34)/'ENTRADAS PMO'!$E$6 -> 0.62857143
A35: 3º lote | B35: 130 | C35: 700 | D35: =C35/SUM($C$32:$C$36) -> 0.22222222 | E35: =B35*C35 -> 91000 | F35: =E35*'ENTRADAS PMO'!$E$13 -> 4550 | G35: =E35*'ENTRADAS PMO'!$E$14 -> 2730 | H35: =E35*'ENTRADAS PMO'!$E$15 -> 0 | I35: =E35-F35-G35-H35 -> 83720 | J35: =SUM($C$32:C35)/'ENTRADAS PMO'!$E$6 -> 0.82857143
A36: Último lote | B36: 150 | C36: 250 | D36: =C36/SUM($C$32:$C$36) -> 0.079365079 | E36: =B36*C36 -> 37500 | F36: =E36*'ENTRADAS PMO'!$E$13 -> 1875 | G36: =E36*'ENTRADAS PMO'!$E$14 -> 1125 | H36: =E36*'ENTRADAS PMO'!$E$15 -> 0 | I36: =E36-F36-G36-H36 -> 34500 | J36: =SUM($C$32:C36)/'ENTRADAS PMO'!$E$6 -> 0.9
A38: Ingressos planejados (pagantes) | C38: =SUM(C32:C36) -> 3150
A39: Ticket médio planejado | C39: =SUM(E32:E36)/SUM(C32:C36) -> 111.03175
A40: Receita bruta planejada | C40: =SUM(E32:E36) -> 349750
A41: Receita líquida planejada | C41: =SUM(I32:I36) -> 321770
A43: ACOMPANHAMENTO DE VENDAS REALIZADO (indicadores de venda)
A44: Data de início das vendas
A45: Data atual | C45: =TODAY() -> 46268
A46: Data do evento
A47: Ingressos vendidos até hoje | C47: 0
A48: Ingressos disponíveis (capacidade Base - vendidos) | C48: ='ENTRADAS PMO'!$D$6-VENDAS!$C$47 -> 3000
A49: % vendido da capacidade Base | C49: =VENDAS!$C$47/'ENTRADAS PMO'!$D$6 -> 0
A50: Receita realizada até hoje (ticket médio Base) | C50: =VENDAS!$C$47*VENDAS!$C$26 -> 0
A51: Meta de vendas (cenário Base) | C51: =VENDAS!$C$25 -> 2850
A52: Gap para a meta | C52: =VENDAS!$C$51-VENDAS!$C$47 -> 2850
A53: Dias decorridos desde o início das vendas | C53: =MAX(1,VENDAS!$C$45-VENDAS!$C$44) -> 46268
A54: Dias restantes até o evento | C54: =MAX(0,VENDAS!$C$46-VENDAS!$C$45) -> 0
A55: Velocidade média de vendas realizada (ingressos/dia) | C55: =VENDAS!$C$47/VENDAS!$C$53 -> 0
A56: Venda diária necessária até o evento | C56: =IF(VENDAS!$C$54=0,0,MAX(0,VENDAS!$C$52)/VENDAS!$C$54) -> 0
A57: Projeção de público final (ritmo atual) | C57: =VENDAS!$C$47+VENDAS!$C$55*VENDAS!$C$54 -> 0

Sheet PATROCINIOS
A1: PIQUINZADA 2027 | PATROCÍNIOS — PIPELINE COMERCIAL
A2: Fonte única dos dados de patrocínio. Estágio define a probabilidade de fechamento automaticamente (tabela abaixo é editável).
A4: PROBABILIDADE PADRÃO POR ESTÁGIO (editável)
A5: Estágio | B5: Probabilidade
A6: Contratado | B6: 1
A7: Proposta Enviada | B7: 0.5
A8: Negociação | B8: 0.3
A9: Prospecção | B9: 0.15
A11: CENÁRIO CONSERVADOR
A12: Cota | B12: Valor unitário | C12: Qtd. alvo | D12: Estágio | E12: Probabilidade | F12: Receita alvo | G12: Receita ponderada | H12: Contrapartida-chave | I12: Perfil de patrocinador
A13: Naming / Apresenta | B13: 51000 | C13: 1 | D13: Negociação | E13: =INDEX($B$6:$B$9,MATCH(D13,$A$6:$A$9,0)) -> 0.3 | F13: =B13*C13 -> 51000 | G13: =F13*E13 -> 15300 | H13: Marca no nome do evento + palco + mídia principal | I13: Banco, bebida, varejo, telecom
A14: Master | B14: 29800 | C14: 2 | D14: Negociação | E14: =INDEX($B$6:$B$9,MATCH(D14,$A$6:$A$9,0)) -> 0.3 | F14: =B14*C14 -> 59600 | G14: =F14*E14 -> 17880 | H14: Alta exposição + ativações + camarote | I14: Bebidas, varejo, construção
A15: Ouro | B15: 17000 | C15: 2 | D15: Negociação | E15: =INDEX($B$6:$B$9,MATCH(D15,$A$6:$A$9,0)) -> 0.3 | F15: =B15*C15 -> 34000 | G15: =F15*E15 -> 10200 | H15: Logo premium + ativações + conteúdo | I15: Empresas regionais e nacionais
A16: Prata | B16: 8500 | C16: 2 | D16: Prospecção | E16: =INDEX($B$6:$B$9,MATCH(D16,$A$6:$A$9,0)) -> 0.15 | F16: =B16*C16 -> 17000 | G16: =F16*E16 -> 2550 | H16: Logo + espaço de ativação | I16: Comércio e serviços
A17: Apoio | B17: 4200 | C17: 3 | D17: Prospecção | E17: =INDEX($B$6:$B$9,MATCH(D17,$A$6:$A$9,0)) -> 0.15 | F17: =B17*C17 -> 12600 | G17: =F17*E17 -> 1890 | H17: Logo em peças selecionadas | I17: Parceiros locais
A19: Nº de cotas comerciais | B19: =SUM(C13:C17) -> 10
A20: Patrocínio contratado (assinado) | B20: =SUMIFS(F13:F17,D13:D17,"Contratado") -> 0
A21: Patrocínio em negociação/pipeline | B21: =SUMIFS(F13:F17,D13:D17,"<>Contratado") -> 174200
A22: Receita ponderada pela probabilidade (esperado) | B22: =SUM(G13:G17) -> 47820
A24: CENÁRIO BASE
A25: Cota | B25: Valor unitário | C25: Qtd. alvo | D25: Estágio | E25: Probabilidade | F25: Receita alvo | G25: Receita ponderada | H25: Contrapartida-chave | I25: Perfil de patrocinador
A26: Naming / Apresenta | B26: 60000 | C26: 1 | D26: Contratado | E26: =INDEX($B$6:$B$9,MATCH(D26,$A$6:$A$9,0)) -> 1 | F26: =B26*C26 -> 60000 | G26: =F26*E26 -> 60000 | H26: Marca no nome do evento + palco + mídia principal | I26: Banco, bebida, varejo, telecom
A27: Master | B27: 35000 | C27: 2 | D27: Proposta Enviada | E27: =INDEX($B$6:$B$9,MATCH(D27,$A$6:$A$9,0)) -> 0.5 | F27: =B27*C27 -> 70000 | G27: =F27*E27 -> 35000 | H27: Alta exposição + ativações + camarote | I27: Bebidas, varejo, construção
A28: Ouro | B28: 20000 | C28: 2 | D28: Proposta Enviada | E28: =INDEX($B$6:$B$9,MATCH(D28,$A$6:$A$9,0)) -> 0.5 | F28: =B28*C28 -> 40000 | G28: =F28*E28 -> 20000 | H28: Logo premium + ativações + conteúdo | I28: Empresas regionais e nacionais
A29: Prata | B29: 10000 | C29: 3 | D29: Negociação | E29: =INDEX($B$6:$B$9,MATCH(D29,$A$6:$A$9,0)) -> 0.3 | F29: =B29*C29 -> 30000 | G29: =F29*E29 -> 9000 | H29: Logo + espaço de ativação | I29: Comércio e serviços
A30: Apoio | B30: 5000 | C30: 4 | D30: Prospecção | E30: =INDEX($B$6:$B$9,MATCH(D30,$A$6:$A$9,0)) -> 0.15 | F30: =B30*C30 -> 20000 | G30: =F30*E30 -> 3000 | H30: Logo em peças selecionadas | I30: Parceiros locais
A32: Nº de cotas comerciais | B32: =SUM(C26:C30) -> 12
A33: Patrocínio contratado (assinado) | B33: =SUMIFS(F26:F30,D26:D30,"Contratado") -> 60000
A34: Patrocínio em negociação/pipeline | B34: =SUMIFS(F26:F30,D26:D30,"<>Contratado") -> 160000
A35: Receita ponderada pela probabilidade (esperado) | B35: =SUM(G26:G30) -> 127000
A37: CENÁRIO AGRESSIVO
A38: Cota | B38: Valor unitário | C38: Qtd. alvo | D38: Estágio | E38: Probabilidade | F38: Receita alvo | G38: Receita ponderada | H38: Contrapartida-chave | I38: Perfil de patrocinador
A39: Naming / Apresenta | B39: 72000 | C39: 1 | D39: Contratado | E39: =INDEX($B$6:$B$9,MATCH(D39,$A$6:$A$9,0)) -> 1 | F39: =B39*C39 -> 72000 | G39: =F39*E39 -> 72000 | H39: Marca no nome do evento + palco + mídia principal | I39: Banco, bebida, varejo, telecom
A40: Master | B40: 42000 | C40: 3 | D40: Contratado | E40: =INDEX($B$6:$B$9,MATCH(D40,$A$6:$A$9,0)) -> 1 | F40: =B40*C40 -> 126000 | G40: =F40*E40 -> 126000 | H40: Alta exposição + ativações + camarote | I40: Bebidas, varejo, construção
A41: Ouro | B41: 24000 | C41: 3 | D41: Proposta Enviada | E41: =INDEX($B$6:$B$9,MATCH(D41,$A$6:$A$9,0)) -> 0.5 | F41: =B41*C41 -> 72000 | G41: =F41*E41 -> 36000 | H41: Logo premium + ativações + conteúdo | I41: Empresas regionais e nacionais
A42: Prata | B42: 12000 | C42: 4 | D42: Negociação | E42: =INDEX($B$6:$B$9,MATCH(D42,$A$6:$A$9,0)) -> 0.3 | F42: =B42*C42 -> 48000 | G42: =F42*E42 -> 14400 | H42: Logo + espaço de ativação | I42: Comércio e serviços
A43: Apoio | B43: 6000 | C43: 5 | D43: Negociação | E43: =INDEX($B$6:$B$9,MATCH(D43,$A$6:$A$9,0)) -> 0.3 | F43: =B43*C43 -> 30000 | G43: =F43*E43 -> 9000 | H43: Logo em peças selecionadas | I43: Parceiros locais
A45: Nº de cotas comerciais | B45: =SUM(C39:C43) -> 16
A46: Patrocínio contratado (assinado) | B46: =SUMIFS(F39:F43,D39:D43,"Contratado") -> 198000
A47: Patrocínio em negociação/pipeline | B47: =SUMIFS(F39:F43,D39:D43,"<>Contratado") -> 150000
A48: Receita ponderada pela probabilidade (esperado) | B48: =SUM(G39:G43) -> 257400

Sheet CUSTOS
A1: PIQUINZADA 2027 | CUSTOS — REGISTRO PMO (BASELINE = CENÁRIO BASE)
A2: Cada linha puxa o Orçamento inicial da aba ENTRADAS PMO (coluna Base). Preencha apenas as colunas azuis conforme a contratação evolui.
A4: Categoria (Grupo) | B4: Subcategoria | C4: Fornecedor | D4: Descrição | E4: Orçamento inicial | F4: Orçamento aprovado | G4: Valor contratado | H4: Valor pago | I4: Saldo a pagar | J4: Data prevista | K4: Data pagamento | L4: Status | M4: Responsável | N4: Observação | O4: EAC do item
A5: Atrações | B5: Cachê atração principal | C5: DJ Marcelinho / Assessoria Ltda. | E5: ='ENTRADAS PMO'!$D$39 -> 180000 | F5: =E5 -> 180000 | G5: 0 | H5: 0 | I5: =G5-H5 -> 0 | J5: 2027-06-01 | L5: Contratado | M5: Comercial | O5: =IF(F5>=G5,F5,G5) -> 180000
A6: Atrações | B6: Cachês das atrações de apoio | E6: ='ENTRADAS PMO'!$D$40 -> 10000 | F6: =E6 -> 10000 | G6: 0 | H6: 0 | I6: =G6-H6 -> 0 | L6: Não iniciado | O6: =IF(F6>=G6,F6,G6) -> 10000
A7: Atrações | B7: DJs | E7: ='ENTRADAS PMO'!$D$41 -> 7500 | F7: =E7 -> 7500 | G7: 0 | H7: 0 | I7: =G7-H7 -> 0 | L7: Não iniciado | O7: =IF(F7>=G7,F7,G7) -> 7500
A8: Atrações | B8: Banda de abertura | E8: ='ENTRADAS PMO'!$D$42 -> 5000 | F8: =E8 -> 5000 | G8: 0 | H8: 0 | I8: =G8-H8 -> 0 | L8: Não iniciado | O8: =IF(F8>=G8,F8,G8) -> 5000
A9: Atrações | B9: Participações especiais | E9: ='ENTRADAS PMO'!$D$43 -> 2500 | F9: =E9 -> 2500 | G9: 0 | H9: 0 | I9: =G9-H9 -> 0 | L9: Não iniciado | O9: =IF(F9>=G9,F9,G9) -> 2500
A10: Estrutura | B10: Palco | E10: ='ENTRADAS PMO'!$D$47 -> 25200 | F10: =E10 -> 25200 | G10: 0 | H10: 0 | I10: =G10-H10 -> 0 | L10: Em cotação | M10: Produção | O10: =IF(F10>=G10,F10,G10) -> 25200
A11: Estrutura | B11: Som | E11: ='ENTRADAS PMO'!$D$48 -> 16200 | F11: =E11 -> 16200 | G11: 0 | H11: 0 | I11: =G11-H11 -> 0 | L11: Em cotação | M11: Produção | O11: =IF(F11>=G11,F11,G11) -> 16200
A12: Estrutura | B12: Iluminação | E12: ='ENTRADAS PMO'!$D$49 -> 12600 | F12: =E12 -> 12600 | G12: 0 | H12: 0 | I12: =G12-H12 -> 0 | L12: Não iniciado | O12: =IF(F12>=G12,F12,G12) -> 12600
A13: Estrutura | B13: Painel de LED | E13: ='ENTRADAS PMO'!$D$50 -> 10800 | F13: =E13 -> 10800 | G13: 0 | H13: 0 | I13: =G13-H13 -> 0 | L13: Não iniciado | O13: =IF(F13>=G13,F13,G13) -> 10800
A14: Estrutura | B14: Gerador | E14: ='ENTRADAS PMO'!$D$51 -> 8100 | F14: =E14 -> 8100 | G14: 0 | H14: 0 | I14: =G14-H14 -> 0 | L14: Não iniciado | O14: =IF(F14>=G14,F14,G14) -> 8100
A15: Estrutura | B15: Banheiros químicos | E15: ='ENTRADAS PMO'!$D$52 -> 5400 | F15: =E15 -> 5400 | G15: 0 | H15: 0 | I15: =G15-H15 -> 0 | L15: Não iniciado | O15: =IF(F15>=G15,F15,G15) -> 5400
A16: Estrutura | B16: Gradil / contenção | E16: ='ENTRADAS PMO'!$D$53 -> 4500 | F16: =E16 -> 4500 | G16: 0 | H16: 0 | I16: =G16-H16 -> 0 | L16: Não iniciado | O16: =IF(F16>=G16,F16,G16) -> 4500
A17: Estrutura | B17: Tendas | E17: ='ENTRADAS PMO'!$D$54 -> 3600 | F17: =E17 -> 3600 | G17: 0 | H17: 0 | I17: =G17-H17 -> 0 | L17: Não iniciado | O17: =IF(F17>=G17,F17,G17) -> 3600
A18: Estrutura | B18: Mobiliário | E18: ='ENTRADAS PMO'!$D$55 -> 1800 | F18: =E18 -> 1800 | G18: 0 | H18: 0 | I18: =G18-H18 -> 0 | L18: Não iniciado | O18: =IF(F18>=G18,F18,G18) -> 1800
A19: Estrutura | B19: Estrutura de camarote | E19: ='ENTRADAS PMO'!$D$56 -> 900 | F19: =E19 -> 900 | G19: 0 | H19: 0 | I19: =G19-H19 -> 0 | L19: Não iniciado | O19: =IF(F19>=G19,F19,G19) -> 900
A20: Estrutura | B20: Decoração | E20: ='ENTRADAS PMO'!$D$57 -> 900 | F20: =E20 -> 900 | G20: 0 | H20: 0 | I20: =G20-H20 -> 0 | L20: Não iniciado | O20: =IF(F20>=G20,F20,G20) -> 900
A21: Segurança | B21: Segurança | E21: ='ENTRADAS PMO'!$D$61 -> 14000 | F21: =E21 -> 14000 | G21: 0 | H21: 0 | I21: =G21-H21 -> 0 | L21: Não iniciado | O21: =IF(F21>=G21,F21,G21) -> 14000
A22: Segurança | B22: Brigadistas | E22: ='ENTRADAS PMO'!$D$62 -> 3500 | F22: =E22 -> 3500 | G22: 0 | H22: 0 | I22: =G22-H22 -> 0 | L22: Não iniciado | O22: =IF(F22>=G22,F22,G22) -> 3500
A23: Segurança | B23: Bombeiro civil | E23: ='ENTRADAS PMO'!$D$63 -> 2500 | F23: =E23 -> 2500 | G23: 0 | H23: 0 | I23: =G23-H23 -> 0 | L23: Não iniciado | O23: =IF(F23>=G23,F23,G23) -> 2500
A24: Segurança | B24: Ambulância / SAMU privado | E24: ='ENTRADAS PMO'!$D$64 -> 2500 | F24: =E24 -> 2500 | G24: 0 | H24: 0 | I24: =G24-H24 -> 0 | L24: Não iniciado | O24: =IF(F24>=G24,F24,G24) -> 2500
A25: Produção | B25: Limpeza | E25: ='ENTRADAS PMO'!$D$65 -> 4500 | F25: =E25 -> 4500 | G25: 0 | H25: 0 | I25: =G25-H25 -> 0 | L25: Não iniciado | O25: =IF(F25>=G25,F25,G25) -> 4500
A26: Produção | B26: Recepção / credenciamento | E26: ='ENTRADAS PMO'!$D$66 -> 3000 | F26: =E26 -> 3000 | G26: 0 | H26: 0 | I26: =G26-H26 -> 0 | L26: Não iniciado | O26: =IF(F26>=G26,F26,G26) -> 3000
A27: Produção | B27: Produção geral | E27: ='ENTRADAS PMO'!$D$67 -> 11000 | F27: =E27 -> 11000 | G27: 0 | H27: 0 | I27: =G27-H27 -> 0 | L27: Não iniciado | O27: =IF(F27>=G27,F27,G27) -> 11000
A28: Produção | B28: Equipe de apoio | E28: ='ENTRADAS PMO'!$D$68 -> 4500 | F28: =E28 -> 4500 | G28: 0 | H28: 0 | I28: =G28-H28 -> 0 | L28: Não iniciado | O28: =IF(F28>=G28,F28,G28) -> 4500
A29: Licenças | B29: Licenças e alvarás | E29: ='ENTRADAS PMO'!$D$69 -> 2000 | F29: =E29 -> 2000 | G29: 0 | H29: 0 | I29: =G29-H29 -> 0 | L29: Não iniciado | O29: =IF(F29>=G29,F29,G29) -> 2000
A30: Licenças | B30: ECAD | E30: ='ENTRADAS PMO'!$D$70 -> 1500 | F30: =E30 -> 1500 | G30: 0 | H30: 0 | I30: =G30-H30 -> 0 | L30: Não iniciado | O30: =IF(F30>=G30,F30,G30) -> 1500
A31: Licenças | B31: Seguro do evento | E31: ='ENTRADAS PMO'!$D$71 -> 1000 | F31: =E31 -> 1000 | G31: 0 | H31: 0 | I31: =G31-H31 -> 0 | L31: Não iniciado | O31: =IF(F31>=G31,F31,G31) -> 1000
A32: Marketing | B32: Tráfego pago | E32: ='ENTRADAS PMO'!$D$75 -> 11200 | F32: =E32 -> 11200 | G32: 0 | H32: 0 | I32: =G32-H32 -> 0 | L32: Não iniciado | O32: =IF(F32>=G32,F32,G32) -> 11200
A33: Marketing | B33: Influenciadores | E33: ='ENTRADAS PMO'!$D$76 -> 5600 | F33: =E33 -> 5600 | G33: 0 | H33: 0 | I33: =G33-H33 -> 0 | L33: Não iniciado | O33: =IF(F33>=G33,F33,G33) -> 5600
A34: Marketing | B34: Designer | E34: ='ENTRADAS PMO'!$D$77 -> 3500 | F34: =E34 -> 3500 | G34: 0 | H34: 0 | I34: =G34-H34 -> 0 | L34: Não iniciado | O34: =IF(F34>=G34,F34,G34) -> 3500
A35: Marketing | B35: Fotografia | E35: ='ENTRADAS PMO'!$D$78 -> 3500 | F35: =E35 -> 3500 | G35: 0 | H35: 0 | I35: =G35-H35 -> 0 | L35: Não iniciado | O35: =IF(F35>=G35,F35,G35) -> 3500
A36: Marketing | B36: Filmagem | E36: ='ENTRADAS PMO'!$D$79 -> 3500 | F36: =E36 -> 3500 | G36: 0 | H36: 0 | I36: =G36-H36 -> 0 | L36: Não iniciado | O36: =IF(F36>=G36,F36,G36) -> 3500
A37: Marketing | B37: Assessoria de imprensa | E37: ='ENTRADAS PMO'!$D$80 -> 2800 | F37: =E37 -> 2800 | G37: 0 | H37: 0 | I37: =G37-H37 -> 0 | L37: Não iniciado | O37: =IF(F37>=G37,F37,G37) -> 2800
A38: Marketing | B38: Mídia (rádio/OOH) | E38: ='ENTRADAS PMO'!$D$81 -> 2800 | F38: =E38 -> 2800 | G38: 0 | H38: 0 | I38: =G38-H38 -> 0 | L38: Não iniciado | O38: =IF(F38>=G38,F38,G38) -> 2800
A39: Marketing | B39: Impressos | E39: ='ENTRADAS PMO'!$D$82 -> 1400 | F39: =E39 -> 1400 | G39: 0 | H39: 0 | I39: =G39-H39 -> 0 | L39: Não iniciado | O39: =IF(F39>=G39,F39,G39) -> 1400
A40: Marketing | B40: Comunicação visual | E40: ='ENTRADAS PMO'!$D$83 -> 700 | F40: =E40 -> 700 | G40: 0 | H40: 0 | I40: =G40-H40 -> 0 | L40: Não iniciado | O40: =IF(F40>=G40,F40,G40) -> 700
A41: Logística | B41: Transporte | E41: ='ENTRADAS PMO'!$D$87 -> 8400 | F41: =E41 -> 8400 | G41: 0 | H41: 0 | I41: =G41-H41 -> 0 | L41: Não iniciado | O41: =IF(F41>=G41,F41,G41) -> 8400
A42: Logística | B42: Passagens | E42: ='ENTRADAS PMO'!$D$88 -> 4500 | F42: =E42 -> 4500 | G42: 0 | H42: 0 | I42: =G42-H42 -> 0 | L42: Não iniciado | O42: =IF(F42>=G42,F42,G42) -> 4500
A43: Logística | B43: Hospedagem | E43: ='ENTRADAS PMO'!$D$89 -> 9000 | F43: =E43 -> 9000 | G43: 0 | H43: 0 | I43: =G43-H43 -> 0 | L43: Não iniciado | O43: =IF(F43>=G43,F43,G43) -> 9000
A44: Logística | B44: Alimentação | E44: ='ENTRADAS PMO'!$D$90 -> 3600 | F44: =E44 -> 3600 | G44: 0 | H44: 0 | I44: =G44-H44 -> 0 | L44: Não iniciado | O44: =IF(F44>=G44,F44,G44) -> 3600
A45: Logística | B45: Camarim | E45: ='ENTRADAS PMO'!$D$91 -> 3000 | F45: =E45 -> 3000 | G45: 0 | H45: 0 | I45: =G45-H45 -> 0 | L45: Não iniciado | O45: =IF(F45>=G45,F45,G45) -> 3000
A46: Logística | B46: Transfers | E46: ='ENTRADAS PMO'!$D$92 -> 1500 | F46: =E46 -> 1500 | G46: 0 | H46: 0 | I46: =G46-H46 -> 0 | L46: Não iniciado | O46: =IF(F46>=G46,F46,G46) -> 1500
A47: Administrativo | B47: Despesas administrativas | E47: ='ENTRADAS PMO'!$D$99 -> 6000 | F47: =E47 -> 6000 | G47: 0 | H47: 0 | I47: =G47-H47 -> 0 | L47: Não iniciado | M47: Financeiro | O47: =IF(F47>=G47,F47,G47) -> 6000
A48: Administrativo | B48: Tributos, taxas bancárias e comissões (sobre a receita) | E48: ='ENTRADAS PMO'!$D$104 -> 24551.325 | F48: =E48 -> 24551.325 | G48: 0 | H48: 0 | I48: =G48-H48 -> 0 | L48: Não iniciado | M48: Financeiro | O48: =IF(F48>=G48,F48,G48) -> 24551.325
A49: Contingência | B49: Reserva de contingência | D49: Reserva para riscos e imprevistos | E49: ='ENTRADAS PMO'!$D$106 -> 35244.106 | F49: =E49 -> 35244.106 | G49: 0 | H49: 0 | I49: =G49-H49 -> 0 | L49: Não iniciado | M49: Financeiro | O49: =IF(F49>=G49,F49,G49) -> 35244.106
A51: INDICADORES DE CONTROLE (PROJECT CONTROLS / EARNED VALUE ADAPTADO)
A52: BAC — Budget at Completion (orçamento total aprovado) | C52: =SUM(F5:F49) -> 475795.43
A53: AC — Actual Cost (custo realizado / pago) | C53: =SUM(H5:H49) -> 0
A54: Valor total contratado | C54: =SUM(G5:G49) -> 0
A55: EAC — Estimate at Completion (maior entre aprovado e contratado, por item) | C55: =SUM(O5:O49) -> 475795.43
A56: ETC — Estimate to Complete (EAC − AC) | C56: =CUSTOS!$C$55-CUSTOS!$C$53 -> 475795.43
A57: VAC — Variance at Completion (BAC − EAC) | C57: =CUSTOS!$C$52-CUSTOS!$C$55 -> 0
A58: % do orçamento comprometido (contratado/BAC) | C58: =CUSTOS!$C$54/CUSTOS!$C$52 -> 0
A59: % efetivamente pago (AC/BAC) | C59: =CUSTOS!$C$53/CUSTOS!$C$52 -> 0

Sheet Cenarios
A1: PIQUINZADA 2027 | MOTOR DE CÁLCULO DOS CENÁRIOS
A2: Aba de cálculo — não editar diretamente. Todos os valores derivam de ENTRADAS PMO, VENDAS, PATROCINIOS e CUSTOS.
A4: PARÂMETROS DE CLASSIFICAÇÃO (editável)
A5: Margem mínima p/ status VERDE | B5: 0.1
A6: Margem de segurança mínima p/ status VERDE | B6: 0.15
A7: Margem abaixo da qual o status é VERMELHO | B7: 0
A9: Cenário | B9: Pagantes | C9: Público total | D9: % Ocupação | E9: Ticket médio | F9: Receita ingressos (líq.) | G9: Receita consumo (líq.) | H9: Patrocínio esperado | I9: Outras receitas | J9: RECEITA TOTAL | K9: CUSTO TOTAL | L9: RESULTADO | M9: MARGEM | N9: Receita/participante | O9: Custo/participante | P9: Contribuição/pagante | Q9: BE ingressos s/ patrocínio | R9: BE ingressos c/ patrocínio | S9: % capacidade p/ BE | T9: Margem de segurança | U9: Patrocínio mínimo p/ cachê | V9: Status | W9: Classificação executiva
A10: Conservador | B10: ='ENTRADAS PMO'!$C$8 -> 1540 | C10: ='ENTRADAS PMO'!$C$9 -> 1660 | D10: ='ENTRADAS PMO'!$C$10 -> 0.75454545 | E10: ='ENTRADAS PMO'!$C$16 -> 80.292208 | F10: ='ENTRADAS PMO'!$C$18 -> 113758 | G10: ='ENTRADAS PMO'!$C$33 -> 33880 | H10: ='ENTRADAS PMO'!$C$24 -> 47820 | I10: ='ENTRADAS PMO'!$C$36 -> 0 | J10: =SUM(F10:I10) -> 195458 | K10: ='ENTRADAS PMO'!$C$107 -> 403049.8 | L10: =J10-K10 -> -207591.8 | M10: =IFERROR(L10/J10,0) -> -1.0620788 | N10: =IFERROR(J10/B10,0) -> 126.92078 | O10: =IFERROR(K10/B10,0) -> 261.72065 | P10: =IFERROR(F10/B10,0)+'ENTRADAS PMO'!$C$30 -> 95.868831 | Q10: =IFERROR(K10/P10,0) -> 4204.1798 | R10: =MAX(0,IFERROR((K10-H10-I10)/P10,0)) -> 3705.3733 | S10: =IFERROR(R10/'ENTRADAS PMO'!$C$6,0) -> 1.6842606 | T10: =IFERROR((B10-R10)/B10,0) -> -1.4060865 | U10: ='ENTRADAS PMO'!$C$39 -> 160000 | V10: =IF(AND(M10>=Cenarios!$B$5,T10>=Cenarios!$B$6),"VERDE",IF(OR(M10<Cenarios!$B$7,T10<0),"VERMELHO","AMARELO")) -> VERMELHO | W10: =IF(V10="VERDE","GO",IF(V10="VERMELHO","NO-GO","GO COM RESSALVAS")) -> NO-GO
A11: Base | B11: ='ENTRADAS PMO'!$D$8 -> 2850 | C11: ='ENTRADAS PMO'!$D$9 -> 3000 | D11: ='ENTRADAS PMO'!$D$10 -> 1 | E11: ='ENTRADAS PMO'!$D$16 -> 106.22456 | F11: ='ENTRADAS PMO'!$D$18 -> 278520.8 | G11: ='ENTRADAS PMO'!$D$33 -> 85505.7 | H11: ='ENTRADAS PMO'!$D$24 -> 127000 | I11: ='ENTRADAS PMO'!$D$36 -> 0 | J11: =SUM(F11:I11) -> 491026.5 | K11: ='ENTRADAS PMO'!$D$107 -> 475795.43 | L11: =J11-K11 -> 15231.069 | M11: =IFERROR(L11/J11,0) -> 0.031018833 | N11: =IFERROR(J11/B11,0) -> 172.29 | O11: =IFERROR(K11/B11,0) -> 166.94577 | P11: =IFERROR(F11/B11,0)+'ENTRADAS PMO'!$D$30 -> 127.7286 | Q11: =IFERROR(K11/P11,0) -> 3725.0502 | R11: =MAX(0,IFERROR((K11-H11-I11)/P11,0)) -> 2730.7544 | S11: =IFERROR(R11/'ENTRADAS PMO'!$D$6,0) -> 0.91025148 | T11: =IFERROR((B11-R11)/B11,0) -> 0.04184055 | U11: ='ENTRADAS PMO'!$D$39 -> 180000 | V11: =IF(AND(M11>=Cenarios!$B$5,T11>=Cenarios!$B$6),"VERDE",IF(OR(M11<Cenarios!$B$7,T11<0),"VERMELHO","AMARELO")) -> AMARELO | W11: =IF(V11="VERDE","GO",IF(V11="VERMELHO","NO-GO","GO COM RESSALVAS")) -> GO COM RESSALVAS
A12: Agressivo | B12: ='ENTRADAS PMO'!$E$8 -> 3150 | C12: ='ENTRADAS PMO'!$E$9 -> 3330 | D12: ='ENTRADAS PMO'!$E$10 -> 0.95142857 | E12: ='ENTRADAS PMO'!$E$16 -> 111.03175 | F12: ='ENTRADAS PMO'!$E$18 -> 321770 | G12: ='ENTRADAS PMO'!$E$33 -> 110250 | H12: ='ENTRADAS PMO'!$E$24 -> 257400 | I12: ='ENTRADAS PMO'!$E$36 -> 0 | J12: =SUM(F12:I12) -> 689420 | K12: ='ENTRADAS PMO'!$E$107 -> 571042.67 | L12: =J12-K12 -> 118377.33 | M12: =IFERROR(L12/J12,0) -> 0.17170568 | N12: =IFERROR(J12/B12,0) -> 218.86349 | O12: =IFERROR(K12/B12,0) -> 181.28339 | P12: =IFERROR(F12/B12,0)+'ENTRADAS PMO'!$E$30 -> 137.14921 | Q12: =IFERROR(K12/P12,0) -> 4163.66 | R12: =MAX(0,IFERROR((K12-H12-I12)/P12,0)) -> 2286.8719 | S12: =IFERROR(R12/'ENTRADAS PMO'!$E$6,0) -> 0.65339198 | T12: =IFERROR((B12-R12)/B12,0) -> 0.27400891 | U12: ='ENTRADAS PMO'!$E$39 -> 200000 | V12: =IF(AND(M12>=Cenarios!$B$5,T12>=Cenarios!$B$6),"VERDE",IF(OR(M12<Cenarios!$B$7,T12<0),"VERMELHO","AMARELO")) -> VERDE | W12: =IF(V12="VERDE","GO",IF(V12="VERMELHO","NO-GO","GO COM RESSALVAS")) -> GO

Sheet ORÇAMENTO x REAL
A1: PIQUINZADA 2027 | ORÇAMENTO x REAL
A2: Rollup automático por categoria. Toda a informação vem da aba CUSTOS — nenhuma célula aqui é digitada manualmente.
A4: Categoria | B4: Orçamento inicial | C4: Orçamento revisado (aprovado) | D4: Valor contratado | E4: Valor realizado (pago) | F4: Saldo | G4: Desvio R$ | H4: Desvio % | I4: Projeção final (EAC) | J4: Classificação
A5: Atrações | B5: =SUMIF(CUSTOS!$A$5:$A$48,$A5,CUSTOS!$E$5:$E$48) -> 205000 | C5: =SUMIF(CUSTOS!$A$5:$A$48,$A5,CUSTOS!$F$5:$F$48) -> 205000 | D5: =SUMIF(CUSTOS!$A$5:$A$48,$A5,CUSTOS!$G$5:$G$48) -> 0 | E5: =SUMIF(CUSTOS!$A$5:$A$48,$A5,CUSTOS!$H$5:$H$48) -> 0 | F5: =C5-E5 -> 205000 | G5: =I5-C5 -> 0 | H5: =IFERROR(G5/C5,0) -> 0 | I5: =SUMIF(CUSTOS!$A$5:$A$48,$A5,CUSTOS!$O$5:$O$48) -> 205000 | J5: =IF(H5<=0,"Dentro do orçamento",IF(H5<=0.05,"Atenção","Estourado")) -> Dentro do orçamento
A6: Estrutura | B6: =SUMIF(CUSTOS!$A$5:$A$48,$A6,CUSTOS!$E$5:$E$48) -> 90000 | C6: =SUMIF(CUSTOS!$A$5:$A$48,$A6,CUSTOS!$F$5:$F$48) -> 90000 | D6: =SUMIF(CUSTOS!$A$5:$A$48,$A6,CUSTOS!$G$5:$G$48) -> 0 | E6: =SUMIF(CUSTOS!$A$5:$A$48,$A6,CUSTOS!$H$5:$H$48) -> 0 | F6: =C6-E6 -> 90000 | G6: =I6-C6 -> 0 | H6: =IFERROR(G6/C6,0) -> 0 | I6: =SUMIF(CUSTOS!$A$5:$A$48,$A6,CUSTOS!$O$5:$O$48) -> 90000 | J6: =IF(H6<=0,"Dentro do orçamento",IF(H6<=0.05,"Atenção","Estourado")) -> Dentro do orçamento
A7: Produção | B7: =SUMIF(CUSTOS!$A$5:$A$48,$A7,CUSTOS!$E$5:$E$48) -> 23000 | C7: =SUMIF(CUSTOS!$A$5:$A$48,$A7,CUSTOS!$F$5:$F$48) -> 23000 | D7: =SUMIF(CUSTOS!$A$5:$A$48,$A7,CUSTOS!$G$5:$G$48) -> 0 | E7: =SUMIF(CUSTOS!$A$5:$A$48,$A7,CUSTOS!$H$5:$H$48) -> 0 | F7: =C7-E7 -> 23000 | G7: =I7-C7 -> 0 | H7: =IFERROR(G7/C7,0) -> 0 | I7: =SUMIF(CUSTOS!$A$5:$A$48,$A7,CUSTOS!$O$5:$O$48) -> 23000 | J7: =IF(H7<=0,"Dentro do orçamento",IF(H7<=0.05,"Atenção","Estourado")) -> Dentro do orçamento
A8: Segurança | B8: =SUMIF(CUSTOS!$A$5:$A$48,$A8,CUSTOS!$E$5:$E$48) -> 22500 | C8: =SUMIF(CUSTOS!$A$5:$A$48,$A8,CUSTOS!$F$5:$F$48) -> 22500 | D8: =SUMIF(CUSTOS!$A$5:$A$48,$A8,CUSTOS!$G$5:$G$48) -> 0 | E8: =SUMIF(CUSTOS!$A$5:$A$48,$A8,CUSTOS!$H$5:$H$48) -> 0 | F8: =C8-E8 -> 22500 | G8: =I8-C8 -> 0 | H8: =IFERROR(G8/C8,0) -> 0 | I8: =SUMIF(CUSTOS!$A$5:$A$48,$A8,CUSTOS!$O$5:$O$48) -> 22500 | J8: =IF(H8<=0,"Dentro do orçamento",IF(H8<=0.05,"Atenção","Estourado")) -> Dentro do orçamento
A9: Marketing | B9: =SUMIF(CUSTOS!$A$5:$A$48,$A9,CUSTOS!$E$5:$E$48) -> 35000 | C9: =SUMIF(CUSTOS!$A$5:$A$48,$A9,CUSTOS!$F$5:$F$48) -> 35000 | D9: =SUMIF(CUSTOS!$A$5:$A$48,$A9,CUSTOS!$G$5:$G$48) -> 0 | E9: =SUMIF(CUSTOS!$A$5:$A$48,$A9,CUSTOS!$H$5:$H$48) -> 0 | F9: =C9-E9 -> 35000 | G9: =I9-C9 -> 0 | H9: =IFERROR(G9/C9,0) -> 0 | I9: =SUMIF(CUSTOS!$A$5:$A$48,$A9,CUSTOS!$O$5:$O$48) -> 35000 | J9: =IF(H9<=0,"Dentro do orçamento",IF(H9<=0.05,"Atenção","Estourado")) -> Dentro do orçamento
A10: Logística | B10: =SUMIF(CUSTOS!$A$5:$A$48,$A10,CUSTOS!$E$5:$E$48) -> 30000 | C10: =SUMIF(CUSTOS!$A$5:$A$48,$A10,CUSTOS!$F$5:$F$48) -> 30000 | D10: =SUMIF(CUSTOS!$A$5:$A$48,$A10,CUSTOS!$G$5:$G$48) -> 0 | E10: =SUMIF(CUSTOS!$A$5:$A$48,$A10,CUSTOS!$H$5:$H$48) -> 0 | F10: =C10-E10 -> 30000 | G10: =I10-C10 -> 0 | H10: =IFERROR(G10/C10,0) -> 0 | I10: =SUMIF(CUSTOS!$A$5:$A$48,$A10,CUSTOS!$O$5:$O$48) -> 30000 | J10: =IF(H10<=0,"Dentro do orçamento",IF(H10<=0.05,"Atenção","Estourado")) -> Dentro do orçamento
A11: Licenças | B11: =SUMIF(CUSTOS!$A$5:$A$48,$A11,CUSTOS!$E$5:$E$48) -> 4500 | C11: =SUMIF(CUSTOS!$A$5:$A$48,$A11,CUSTOS!$F$5:$F$48) -> 4500 | D11: =SUMIF(CUSTOS!$A$5:$A$48,$A11,CUSTOS!$G$5:$G$48) -> 0 | E11: =SUMIF(CUSTOS!$A$5:$A$48,$A11,CUSTOS!$H$5:$H$48) -> 0 | F11: =C11-E11 -> 4500 | G11: =I11-C11 -> 0 | H11: =IFERROR(G11/C11,0) -> 0 | I11: =SUMIF(CUSTOS!$A$5:$A$48,$A11,CUSTOS!$O$5:$O$48) -> 4500 | J11: =IF(H11<=0,"Dentro do orçamento",IF(H11<=0.05,"Atenção","Estourado")) -> Dentro do orçamento
A12: Administrativo | B12: =SUMIF(CUSTOS!$A$5:$A$48,$A12,CUSTOS!$E$5:$E$48) -> 30551.325 | C12: =SUMIF(CUSTOS!$A$5:$A$48,$A12,CUSTOS!$F$5:$F$48) -> 30551.325 | D12: =SUMIF(CUSTOS!$A$5:$A$48,$A12,CUSTOS!$G$5:$G$48) -> 0 | E12: =SUMIF(CUSTOS!$A$5:$A$48,$A12,CUSTOS!$H$5:$H$48) -> 0 | F12: =C12-E12 -> 30551.325 | G12: =I12-C12 -> 0 | H12: =IFERROR(G12/C12,0) -> 0 | I12: =SUMIF(CUSTOS!$A$5:$A$48,$A12,CUSTOS!$O$5:$O$48) -> 30551.325 | J12: =IF(H12<=0,"Dentro do orçamento",IF(H12<=0.05,"Atenção","Estourado")) -> Dentro do orçamento
A13: Contingência | B13: =SUMIF(CUSTOS!$A$5:$A$48,$A13,CUSTOS!$E$5:$E$48) -> 0 | C13: =SUMIF(CUSTOS!$A$5:$A$48,$A13,CUSTOS!$F$5:$F$48) -> 0 | D13: =SUMIF(CUSTOS!$A$5:$A$48,$A13,CUSTOS!$G$5:$G$48) -> 0 | E13: =SUMIF(CUSTOS!$A$5:$A$48,$A13,CUSTOS!$H$5:$H$48) -> 0 | F13: =C13-E13 -> 0 | G13: =I13-C13 -> 0 | H13: =IFERROR(G13/C13,0) -> 0 | I13: =SUMIF(CUSTOS!$A$5:$A$48,$A13,CUSTOS!$O$5:$O$48) -> 0 | J13: =IF(H13<=0,"Dentro do orçamento",IF(H13<=0.05,"Atenção","Estourado")) -> Dentro do orçamento
A14: TOTAL | B14: =SUM(B5:B13) -> 440551.33 | C14: =SUM(C5:C13) -> 440551.33 | D14: =SUM(D5:D13) -> 0 | E14: =SUM(E5:E13) -> 0 | F14: =SUM(F5:F13) -> 440551.33 | G14: =SUM(G5:G13) -> 0 | H14: =IFERROR(G14/C14,0) -> 0 | I14: =SUM(I5:I13) -> 440551.33

Sheet FLUXO DE CAIXA
A1: PIQUINZADA 2027 | FLUXO DE CAIXA
A2: Distribua o % de cada linha ao longo dos meses (deve somar 100%). Os totais anuais vêm do cenário selecionado abaixo.
A4: Cenário de referência | B4: Base
A5: Saldo inicial de caixa | B5: 0
A6: Coluna do cenário (auto) | B6: =IF('FLUXO DE CAIXA'!$B$4="Conservador","C",IF('FLUXO DE CAIXA'!$B$4="Base","D","E")) -> D
A8: Linha | B8: Jan | C8: Fev | D8: Mar | E8: Abr | F8: Mai | G8: Jun | H8: Jul | I8: Ago | J8: Set | K8: Out | L8: Nov | M8: Dez | N8: Total ano
A9: ENTRADAS
A10: Ingressos | B10: 0 | C10: 0.05 | D10: 0.1 | E10: 0.1 | F10: 0.1 | G10: 0.05 | H10: 0.05 | I10: 0.05 | J10: 0.1 | K10: 0.15 | L10: 0.15 | M10: 0.1 | N10: =SUM(B10:M10) -> 1
A11: Patrocínios | B11: 0.05 | C11: 0.1 | D11: 0.15 | E11: 0.15 | F11: 0.1 | G11: 0.05 | H11: 0.05 | I11: 0.05 | J11: 0.1 | K11: 0.1 | L11: 0.05 | M11: 0.05 | N11: =SUM(B11:M11) -> 1
A12: Bar / Ativações | B12: 0 | C12: 0 | D12: 0 | E12: 0 | F12: 0 | G12: 0 | H12: 0 | I12: 0 | J12: 0 | K12: 0 | L12: 0 | M12: 1 | N12: =SUM(B12:M12) -> 1
A13: Outras receitas | B13: 0 | C13: 0 | D13: 0 | E13: 0 | F13: 0 | G13: 0 | H13: 0 | I13: 0 | J13: 0 | K13: 0 | L13: 0.5 | M13: 0.5 | N13: =SUM(B13:M13) -> 1
A14: TOTAL ENTRADAS (R$) | B14: =SUM(B28:B31) -> 6350 | C14: =SUM(C28:C31) -> 26626.04 | D14: =SUM(D28:D31) -> 46902.08 | E14: =SUM(E28:E31) -> 46902.08 | F14: =SUM(F28:F31) -> 40552.08 | G14: =SUM(G28:G31) -> 20276.04 | H14: =SUM(H28:H31) -> 20276.04 | I14: =SUM(I28:I31) -> 20276.04 | ... M14: =SUM(M28:M31) -> 119707.78 | N14: =SUM(B14:M14) -> 491026.5
A16: SAÍDAS
A17: Atrações (cachês) | B17: 0 | C17: 0.2 | D17: 0 | E17: 0 | F17: 0 | G17: 0 | H17: 0 | I17: 0 | J17: 0 | K17: 0 | L17: 0.3 | M17: 0.5 | N17: =SUM(B17:M17) -> 1
A18: Estrutura | B18: 0 | C18: 0 | D18: 0 | E18: 0 | F18: 0 | G18: 0 | H18: 0 | I18: 0 | J18: 0.1 | K18: 0.2 | L18: 0.3 | M18: 0.4 | N18: =SUM(B18:M18) -> 1
A19: Operação (produção/segurança/licenças) | B19: 0 | C19: 0 | D19: 0 | E19: 0 | F19: 0 | G19: 0 | H19: 0 | I19: 0 | J19: 0.05 | K19: 0.15 | L19: 0.3 | M19: 0.5 | N19: =SUM(B19:M19) -> 1
A20: Marketing | B20: 0.05 | C20: 0.05 | D20: 0.05 | E20: 0.05 | F20: 0.1 | G20: 0.1 | H20: 0.1 | I20: 0.1 | J20: 0.1 | K20: 0.1 | L20: 0.1 | M20: 0.1 | N20: =SUM(B20:M20) -> 1
A21: Logística | B21: 0 | C21: 0 | D21: 0 | E21: 0 | F21: 0 | G21: 0 | H21: 0 | I21: 0 | J21: 0.1 | K21: 0.2 | L21: 0.3 | M21: 0.4 | N21: =SUM(B21:M21) -> 1
A22: Administrativo | B22: 0.08 | C22: 0.08 | D22: 0.08 | E22: 0.08 | F22: 0.09 | G22: 0.09 | H22: 0.09 | I22: 0.09 | J22: 0.09 | K22: 0.08 | L22: 0.08 | M22: 0.07 | N22: =SUM(B22:M22) -> 1
A23: Taxas / tributos / comissões | B23: 0 | C23: 0 | D23: 0 | E23: 0 | F23: 0 | G23: 0 | H23: 0 | I23: 0 | J23: 0 | K23: 0.2 | L23: 0.4 | M23: 0.4 | N23: =SUM(B23:M23) -> 1
A24: Contingência | B24: 0 | C24: 0 | D24: 0 | E24: 0 | F24: 0 | G24: 0 | H24: 0 | I24: 0 | J24: 0 | K24: 0.2 | L24: 0.3 | M24: 0.5 | N24: =SUM(B24:M24) -> 1
A25: TOTAL SAÍDAS (R$) | B25: =SUM(B32:B39) -> 2230 | C25: =SUM(C32:C39) -> 43230 | D25: =SUM(D32:D39) -> 2230 | E25: =SUM(E32:E39) -> 2230 | F25: =SUM(F32:F39) -> 4040 | G25: =SUM(G32:G39) -> 4040 | H25: =SUM(H32:H39) -> 4040 | I25: =SUM(I32:I39) -> 4040 | ... M25: =SUM(M32:M39) -> 206862.58 | N25: =SUM(B25:M25) -> 475795.43
A27: VALORES MENSAIS EM R$ (calculado)
A28: Ingressos | B28: =INDIRECT("'ENTRADAS PMO'!"&'FLUXO DE CAIXA'!$B$6&"18")*B10 -> 0 | C28: =INDIRECT("'ENTRADAS PMO'!"&'FLUXO DE CAIXA'!$B$6&"18")*C10 -> 13926.04 | D28: =INDIRECT("'ENTRADAS PMO'!"&'FLUXO DE CAIXA'!$B$6&"18")*D10 -> 27852.08 | E28: =INDIRECT("'ENTRADAS PMO'!"&'FLUXO DE CAIXA'!$B$6&"18")*E10 -> 27852.08 | F28: =INDIRECT("'ENTRADAS PMO'!"&'FLUXO DE CAIXA'!$B$6&"18")*F10 -> 27852.08 | G28: =INDIRECT("'ENTRADAS PMO'!"&'FLUXO DE CAIXA'!$B$6&"18")*G10 -> 13926.04 | H28: =INDIRECT("'ENTRADAS PMO'!"&'FLUXO DE CAIXA'!$B$6&"18")*H10 -> 13926.04 | I28: =INDIRECT("'ENTRADAS PMO'!"&'FLUXO DE CAIXA'!$B$6&"18")*I10 -> 13926.04 | ... M28: =INDIRECT("'ENTRADAS PMO'!"&'FLUXO DE CAIXA'!$B$6&"18")*M10 -> 27852.08 | N28: =SUM(B28:M28) -> 278520.8
A29: Patrocínios | B29: =INDIRECT("'ENTRADAS PMO'!"&'FLUXO DE CAIXA'!$B$6&"24")*B11 -> 6350 | C29: =INDIRECT("'ENTRADAS PMO'!"&'FLUXO DE CAIXA'!$B$6&"24")*C11 -> 12700 | D29: =INDIRECT("'ENTRADAS PMO'!"&'FLUXO DE CAIXA'!$B$6&"24")*D11 -> 19050 | E29: =INDIRECT("'ENTRADAS PMO'!"&'FLUXO DE CAIXA'!$B$6&"24")*E11 -> 19050 | F29: =INDIRECT("'ENTRADAS PMO'!"&'FLUXO DE CAIXA'!$B$6&"24")*F11 -> 12700 | G29: =INDIRECT("'ENTRADAS PMO'!"&'FLUXO DE CAIXA'!$B$6&"24")*G11 -> 6350 | H29: =INDIRECT("'ENTRADAS PMO'!"&'FLUXO DE CAIXA'!$B$6&"24")*H11 -> 6350 | I29: =INDIRECT("'ENTRADAS PMO'!"&'FLUXO DE CAIXA'!$B$6&"24")*I11 -> 6350 | ... M29: =INDIRECT("'ENTRADAS PMO'!"&'FLUXO DE CAIXA'!$B$6&"24")*M11 -> 6350 | N29: =SUM(B29:M29) -> 127000
A30: Bar / Ativações | B30: =INDIRECT("'ENTRADAS PMO'!"&'FLUXO DE CAIXA'!$B$6&"33")*B12 -> 0 | C30: =INDIRECT("'ENTRADAS PMO'!"&'FLUXO DE CAIXA'!$B$6&"33")*C12 -> 0 | D30: =INDIRECT("'ENTRADAS PMO'!"&'FLUXO DE CAIXA'!$B$6&"33")*D12 -> 0 | E30: =INDIRECT("'ENTRADAS PMO'!"&'FLUXO DE CAIXA'!$B$6&"33")*E12 -> 0 | F30: =INDIRECT("'ENTRADAS PMO'!"&'FLUXO DE CAIXA'!$B$6&"33")*F12 -> 0 | G30: =INDIRECT("'ENTRADAS PMO'!"&'FLUXO DE CAIXA'!$B$6&"33")*G12 -> 0 | H30: =INDIRECT("'ENTRADAS PMO'!"&'FLUXO DE CAIXA'!$B$6&"33")*H12 -> 0 | I30: =INDIRECT("'ENTRADAS PMO'!"&'FLUXO DE CAIXA'!$B$6&"33")*I12 -> 0 | ... M30: =INDIRECT("'ENTRADAS PMO'!"&'FLUXO DE CAIXA'!$B$6&"33")*M12 -> 85505.7 | N30: =SUM(B30:M30) -> 85505.7
A31: Outras receitas | B31: =INDIRECT("'ENTRADAS PMO'!"&'FLUXO DE CAIXA'!$B$6&"36")*B13 -> 0 | C31: =INDIRECT("'ENTRADAS PMO'!"&'FLUXO DE CAIXA'!$B$6&"36")*C13 -> 0 | D31: =INDIRECT("'ENTRADAS PMO'!"&'FLUXO DE CAIXA'!$B$6&"36")*D13 -> 0 | E31: =INDIRECT("'ENTRADAS PMO'!"&'FLUXO DE CAIXA'!$B$6&"36")*E13 -> 0 | F31: =INDIRECT("'ENTRADAS PMO'!"&'FLUXO DE CAIXA'!$B$6&"36")*F13 -> 0 | G31: =INDIRECT("'ENTRADAS PMO'!"&'FLUXO DE CAIXA'!$B$6&"36")*G13 -> 0 | H31: =INDIRECT("'ENTRADAS PMO'!"&'FLUXO DE CAIXA'!$B$6&"36")*H13 -> 0 | I31: =INDIRECT("'ENTRADAS PMO'!"&'FLUXO DE CAIXA'!$B$6&"36")*I13 -> 0 | ... M31: =INDIRECT("'ENTRADAS PMO'!"&'FLUXO DE CAIXA'!$B$6&"36")*M13 -> 0 | N31: =SUM(B31:M31) -> 0
A32: Atrações (cachês) | B32: =INDIRECT("'ENTRADAS PMO'!"&'FLUXO DE CAIXA'!$B$6&"44")*B17 -> 0 | C32: =INDIRECT("'ENTRADAS PMO'!"&'FLUXO DE CAIXA'!$B$6&"44")*C17 -> 41000 | D32: =INDIRECT("'ENTRADAS PMO'!"&'FLUXO DE CAIXA'!$B$6&"44")*D17 -> 0 | E32: =INDIRECT("'ENTRADAS PMO'!"&'FLUXO DE CAIXA'!$B$6&"44")*E17 -> 0 | F32: =INDIRECT("'ENTRADAS PMO'!"&'FLUXO DE CAIXA'!$B$6&"44")*F17 -> 0 | G32: =INDIRECT("'ENTRADAS PMO'!"&'FLUXO DE CAIXA'!$B$6&"44")*G17 -> 0 | H32: =INDIRECT("'ENTRADAS PMO'!"&'FLUXO DE CAIXA'!$B$6&"44")*H17 -> 0 | I32: =INDIRECT("'ENTRADAS PMO'!"&'FLUXO DE CAIXA'!$B$6&"44")*I17 -> 0 | ... M32: =INDIRECT("'ENTRADAS PMO'!"&'FLUXO DE CAIXA'!$B$6&"44")*M17 -> 102500 | N32: =SUM(B32:M32) -> 205000
A33: Estrutura | B33: =INDIRECT("'ENTRADAS PMO'!"&'FLUXO DE CAIXA'!$B$6&"58")*B18 -> 0 | C33: =INDIRECT("'ENTRADAS PMO'!"&'FLUXO DE CAIXA'!$B$6&"58")*C18 -> 0 | D33: =INDIRECT("'ENTRADAS PMO'!"&'FLUXO DE CAIXA'!$B$6&"58")*D18 -> 0 | E33: =INDIRECT("'ENTRADAS PMO'!"&'FLUXO DE CAIXA'!$B$6&"58")*E18 -> 0 | F33: =INDIRECT("'ENTRADAS PMO'!"&'FLUXO DE CAIXA'!$B$6&"58")*F18 -> 0 | G33: =INDIRECT("'ENTRADAS PMO'!"&'FLUXO DE CAIXA'!$B$6&"58")*G18 -> 0 | H33: =INDIRECT("'ENTRADAS PMO'!"&'FLUXO DE CAIXA'!$B$6&"58")*H18 -> 0 | I33: =INDIRECT("'ENTRADAS PMO'!"&'FLUXO DE CAIXA'!$B$6&"58")*I18 -> 0 | ... M33: =INDIRECT("'ENTRADAS PMO'!"&'FLUXO DE CAIXA'!$B$6&"58")*M18 -> 36000 | N33: =SUM(B33:M33) -> 90000
A34: Operação (produção/segurança/licenças) | B34: =INDIRECT("'ENTRADAS PMO'!"&'FLUXO DE CAIXA'!$B$6&"72")*B19 -> 0 | C34: =INDIRECT("'ENTRADAS PMO'!"&'FLUXO DE CAIXA'!$B$6&"72")*C19 -> 0 | D34: =INDIRECT("'ENTRADAS PMO'!"&'FLUXO DE CAIXA'!$B$6&"72")*D19 -> 0 | E34: =INDIRECT("'ENTRADAS PMO'!"&'FLUXO DE CAIXA'!$B$6&"72")*E19 -> 0 | F34: =INDIRECT("'ENTRADAS PMO'!"&'FLUXO DE CAIXA'!$B$6&"72")*F19 -> 0 | G34: =INDIRECT("'ENTRADAS PMO'!"&'FLUXO DE CAIXA'!$B$6&"72")*G19 -> 0 | H34: =INDIRECT("'ENTRADAS PMO'!"&'FLUXO DE CAIXA'!$B$6&"72")*H19 -> 0 | I34: =INDIRECT("'ENTRADAS PMO'!"&'FLUXO DE CAIXA'!$B$6&"72")*I19 -> 0 | ... M34: =INDIRECT("'ENTRADAS PMO'!"&'FLUXO DE CAIXA'!$B$6&"72")*M19 -> 25000 | N34: =SUM(B34:M34) -> 50000
A35: Marketing | B35: =INDIRECT("'ENTRADAS PMO'!"&'FLUXO DE CAIXA'!$B$6&"84")*B20 -> 1750 | C35: =INDIRECT("'ENTRADAS PMO'!"&'FLUXO DE CAIXA'!$B$6&"84")*C20 -> 1750 | D35: =INDIRECT("'ENTRADAS PMO'!"&'FLUXO DE CAIXA'!$B$6&"84")*D20 -> 1750 | E35: =INDIRECT("'ENTRADAS PMO'!"&'FLUXO DE CAIXA'!$B$6&"84")*E20 -> 1750 | F35: =INDIRECT("'ENTRADAS PMO'!"&'FLUXO DE CAIXA'!$B$6&"84")*F20 -> 3500 | G35: =INDIRECT("'ENTRADAS PMO'!"&'FLUXO DE CAIXA'!$B$6&"84")*G20 -> 3500 | H35: =INDIRECT("'ENTRADAS PMO'!"&'FLUXO DE CAIXA'!$B$6&"84")*H20 -> 3500 | I35: =INDIRECT("'ENTRADAS PMO'!"&'FLUXO DE CAIXA'!$B$6&"84")*I20 -> 3500 | ... M35: =INDIRECT("'ENTRADAS PMO'!"&'FLUXO DE CAIXA'!$B$6&"84")*M20 -> 3500 | N35: =SUM(B35:M35) -> 35000
A36: Logística | B36: =INDIRECT("'ENTRADAS PMO'!"&'FLUXO DE CAIXA'!$B$6&"93")*B21 -> 0 | C36: =INDIRECT("'ENTRADAS PMO'!"&'FLUXO DE CAIXA'!$B$6&"93")*C21 -> 0 | D36: =INDIRECT("'ENTRADAS PMO'!"&'FLUXO DE CAIXA'!$B$6&"93")*D21 -> 0 | E36: =INDIRECT("'ENTRADAS PMO'!"&'FLUXO DE CAIXA'!$B$6&"93")*E21 -> 0 | F36: =INDIRECT("'ENTRADAS PMO'!"&'FLUXO DE CAIXA'!$B$6&"93")*F21 -> 0 | G36: =INDIRECT("'ENTRADAS PMO'!"&'FLUXO DE CAIXA'!$B$6&"93")*G21 -> 0 | H36: =INDIRECT("'ENTRADAS PMO'!"&'FLUXO DE CAIXA'!$B$6&"93")*H21 -> 0 | I36: =INDIRECT("'ENTRADAS PMO'!"&'FLUXO DE CAIXA'!$B$6&"93")*I21 -> 0 | ... M36: =INDIRECT("'ENTRADAS PMO'!"&'FLUXO DE CAIXA'!$B$6&"93")*M21 -> 12000 | N36: =SUM(B36:M36) -> 30000
A37: Administrativo | B37: =INDIRECT("'ENTRADAS PMO'!"&'FLUXO DE CAIXA'!$B$6&"99")*B22 -> 480 | C37: =INDIRECT("'ENTRADAS PMO'!"&'FLUXO DE CAIXA'!$B$6&"99")*C22 -> 480 | D37: =INDIRECT("'ENTRADAS PMO'!"&'FLUXO DE CAIXA'!$B$6&"99")*D22 -> 480 | E37: =INDIRECT("'ENTRADAS PMO'!"&'FLUXO DE CAIXA'!$B$6&"99")*E22 -> 480 | F37: =INDIRECT("'ENTRADAS PMO'!"&'FLUXO DE CAIXA'!$B$6&"99")*F22 -> 540 | G37: =INDIRECT("'ENTRADAS PMO'!"&'FLUXO DE CAIXA'!$B$6&"99")*G22 -> 540 | H37: =INDIRECT("'ENTRADAS PMO'!"&'FLUXO DE CAIXA'!$B$6&"99")*H22 -> 540 | I37: =INDIRECT("'ENTRADAS PMO'!"&'FLUXO DE CAIXA'!$B$6&"99")*I22 -> 540 | ... M37: =INDIRECT("'ENTRADAS PMO'!"&'FLUXO DE CAIXA'!$B$6&"99")*M22 -> 420 | N37: =SUM(B37:M37) -> 6000
A38: Taxas / tributos / comissões | B38: =INDIRECT("'ENTRADAS PMO'!"&'FLUXO DE CAIXA'!$B$6&"104")*B23 -> 0 | C38: =INDIRECT("'ENTRADAS PMO'!"&'FLUXO DE CAIXA'!$B$6&"104")*C23 -> 0 | D38: =INDIRECT("'ENTRADAS PMO'!"&'FLUXO DE CAIXA'!$B$6&"104")*D23 -> 0 | E38: =INDIRECT("'ENTRADAS PMO'!"&'FLUXO DE CAIXA'!$B$6&"104")*E23 -> 0 | F38: =INDIRECT("'ENTRADAS PMO'!"&'FLUXO DE CAIXA'!$B$6&"104")*F23 -> 0 | G38: =INDIRECT("'ENTRADAS PMO'!"&'FLUXO DE CAIXA'!$B$6&"104")*G23 -> 0 | H38: =INDIRECT("'ENTRADAS PMO'!"&'FLUXO DE CAIXA'!$B$6&"104")*H23 -> 0 | I38: =INDIRECT("'ENTRADAS PMO'!"&'FLUXO DE CAIXA'!$B$6&"104")*I23 -> 0 | ... M38: =INDIRECT("'ENTRADAS PMO'!"&'FLUXO DE CAIXA'!$B$6&"104")*M23 -> 9820.53 | N38: =SUM(B38:M38) -> 24551.325
A39: Contingência | B39: =INDIRECT("'ENTRADAS PMO'!"&'FLUXO DE CAIXA'!$B$6&"106")*B24 -> 0 | C39: =INDIRECT("'ENTRADAS PMO'!"&'FLUXO DE CAIXA'!$B$6&"106")*C24 -> 0 | D39: =INDIRECT("'ENTRADAS PMO'!"&'FLUXO DE CAIXA'!$B$6&"106")*D24 -> 0 | E39: =INDIRECT("'ENTRADAS PMO'!"&'FLUXO DE CAIXA'!$B$6&"106")*E24 -> 0 | F39: =INDIRECT("'ENTRADAS PMO'!"&'FLUXO DE CAIXA'!$B$6&"106")*F24 -> 0 | G39: =INDIRECT("'ENTRADAS PMO'!"&'FLUXO DE CAIXA'!$B$6&"106")*G24 -> 0 | H39: =INDIRECT("'ENTRADAS PMO'!"&'FLUXO DE CAIXA'!$B$6&"106")*H24 -> 0 | I39: =INDIRECT("'ENTRADAS PMO'!"&'FLUXO DE CAIXA'!$B$6&"106")*I24 -> 0 | ... M39: =INDIRECT("'ENTRADAS PMO'!"&'FLUXO DE CAIXA'!$B$6&"106")*M24 -> 17622.053 | N39: =SUM(B39:M39) -> 35244.106
A41: SALDO DE CAIXA
A42: Saldo do período | B42: =B14-B25 -> 4120 | C42: =C14-C25 -> -16603.96 | D42: =D14-D25 -> 44672.08 | E42: =E14-E25 -> 44672.08 | F42: =F14-F25 -> 36512.08 | G42: =G14-G25 -> 16236.04 | H42: =H14-H25 -> 16236.04 | I42: =I14-I25 -> 16236.04 | ... M42: =M14-M25 -> -87154.803 | N42: =SUM(B42:M42) -> 15231.069
A43: Saldo acumulado | B43: ='FLUXO DE CAIXA'!$B$5+B42 -> 4120 | C43: =B43+C42 -> -12483.96 | D43: =C43+D42 -> 32188.12 | E43: =D43+E42 -> 76860.2 | F43: =E43+F42 -> 113372.28 | G43: =F43+G42 -> 129608.32 | H43: =G43+H42 -> 145844.36 | I43: =H43+I42 -> 162080.4 | J43: =I43+J42 -> 184092.48 | ... M43: =L43+M42 -> 15231.069
A45: Necessidade máxima de capital de giro | B45: =MAX(0,-MIN(B43:M43)) -> 12483.96
A46: Resultado final do exercício (lucro/prejuízo) | B46: =N14-N25 -> 15231.069
A47: ALERTA DE CAIXA | B47: =IF(AND(B46>0,MIN(B43:M43)<0),"⚠ RISCO: projeto lucrativo no total, mas há déficit de caixa antes/durante o evento — capital de giro necessário",IF(MIN(B43:M43)<0,"⚠ RISCO: caixa fica negativo em algum mês","OK — caixa positivo em todos os meses")) -> ⚠ RISCO: projeto lucrativo no total, mas há déficit de caixa antes/durante o evento — capital de giro necessário
A49: DETALHAMENTO SEMANAL — MÊS DO EVENTO (últimas 8 semanas, mês = Dez)
A50: Distribua o total do mês do evento (coluna "Dez" acima) entre as 8 semanas que o antecedem. Útil para checar caixa na reta final.
A51: Linha | B51: Sem. -7 | C51: Sem. -6 | D51: Sem. -5 | E51: Sem. -4 | F51: Sem. -3 | G51: Sem. -2 | H51: Sem. -1 | I51: Sem. Evento | J51: Total
A52: % Entradas por semana | B52: 0.05 | C52: 0.05 | D52: 0.08 | E52: 0.08 | F52: 0.1 | G52: 0.12 | H52: 0.22 | I52: 0.3 | J52: =SUM(B52:I52) -> 1
A53: % Saídas por semana | B53: 0.05 | C53: 0.05 | D53: 0.08 | E53: 0.1 | F53: 0.12 | G53: 0.15 | H53: 0.2 | I53: 0.25 | J53: =SUM(B53:I53) -> 1
A54: Entradas (R$) | B54: =$N$14*B52 -> 24551.325 | C54: =$N$14*C52 -> 24551.325 | D54: =$N$14*D52 -> 39282.12 | E54: =$N$14*E52 -> 39282.12 | F54: =$N$14*F52 -> 49102.65 | G54: =$N$14*G52 -> 58923.18 | H54: =$N$14*H52 -> 108025.83 | I54: =$N$14*I52 -> 147307.95 | J54: =SUM(B54:I54) -> 491026.5
A55: Saídas (R$) | B55: =$N$25*B53 -> 23789.772 | C55: =$N$25*C53 -> 23789.772 | D55: =$N$25*D53 -> 38063.634 | E55: =$N$25*E53 -> 47579.543 | F55: =$N$25*F53 -> 57095.452 | G55: =$N$25*G53 -> 71369.315 | H55: =$N$25*H53 -> 95159.086 | I55: =$N$25*I53 -> 118948.86 | J55: =SUM(B55:I55) -> 475795.43
A56: Saldo acumulado (semanal) | B56: =L43+B54-B55 -> 103147.43 | C56: =B56+C54-C55 -> 103908.98 | D56: =C56+D54-D55 -> 105127.46 | E56: =D56+E54-E55 -> 96830.041 | F56: =E56+F54-F55 -> 88837.24 | G56: =F56+G54-G55 -> 76391.105 | H56: =G56+H54-H55 -> 89257.849 | I56: =H56+I54-I55 -> 117616.94
A59: CAPITAL DE GIRO POR CENÁRIO (reutiliza as mesmas distribuições mensais acima)
A60: Aplica os % de distribuição mensal definidos acima aos totais de cada cenário, para comparar a necessidade de caixa entre eles.
A61: Conservador — Saldo acumulado mensal | B61: ='FLUXO DE CAIXA'!$B$5+(('ENTRADAS PMO'!$C$18*B10+'ENTRADAS PMO'!$C$24*B11+'ENTRADAS PMO'!$C$33*B12+'ENTRADAS PMO'!$C$36*B13)-('ENTRADAS PMO'!$C$44*B17+'ENTRADAS PMO'!$C$58*B18+'ENTRADAS PMO'!$C$72*B19+'ENTRADAS PMO'!$C$84*B20+'ENTRADAS PMO'!$C$93*B21+'ENTRADAS PMO'!$C$99*B22+'ENTRADAS PMO'!$C$104*B23+'ENTRADAS PMO'!$C$106*B24)) -> 501 | C61: =B61+(('ENTRADAS PMO'!$C$18*C10+'ENTRADAS PMO'!$C$24*C11+'ENTRADAS PMO'!$C$33*C12+'ENTRADAS PMO'!$C$36*C13)-('ENTRADAS PMO'!$C$44*C17+'ENTRADAS PMO'!$C$58*C18+'ENTRADAS PMO'!$C$72*C19+'ENTRADAS PMO'!$C$84*C20+'ENTRADAS PMO'!$C$93*C21+'ENTRADAS PMO'!$C$99*C22+'ENTRADAS PMO'!$C$104*C23+'ENTRADAS PMO'!$C$106*C24)) -> -26919.1 | D61: =C61+(('ENTRADAS PMO'!$C$18*D10+'ENTRADAS PMO'!$C$24*D11+'ENTRADAS PMO'!$C$33*D12+'ENTRADAS PMO'!$C$36*D13)-('ENTRADAS PMO'!$C$44*D17+'ENTRADAS PMO'!$C$58*D18+'ENTRADAS PMO'!$C$72*D19+'ENTRADAS PMO'!$C$84*D20+'ENTRADAS PMO'!$C$93*D21+'ENTRADAS PMO'!$C$99*D22+'ENTRADAS PMO'!$C$104*D23+'ENTRADAS PMO'!$C$106*D24)) -> -10260.3 | E61: =D61+(('ENTRADAS PMO'!$C$18*E10+'ENTRADAS PMO'!$C$24*E11+'ENTRADAS PMO'!$C$33*E12+'ENTRADAS PMO'!$C$36*E13)-('ENTRADAS PMO'!$C$44*E17+'ENTRADAS PMO'!$C$58*E18+'ENTRADAS PMO'!$C$72*E19+'ENTRADAS PMO'!$C$84*E20+'ENTRADAS PMO'!$C$93*E21+'ENTRADAS PMO'!$C$99*E22+'ENTRADAS PMO'!$C$104*E23+'ENTRADAS PMO'!$C$106*E24)) -> 6398.5 | F61: =E61+(('ENTRADAS PMO'!$C$18*F10+'ENTRADAS PMO'!$C$24*F11+'ENTRADAS PMO'!$C$33*F12+'ENTRADAS PMO'!$C$36*F13)-('ENTRADAS PMO'!$C$44*F17+'ENTRADAS PMO'!$C$58*F18+'ENTRADAS PMO'!$C$72*F19+'ENTRADAS PMO'!$C$84*F20+'ENTRADAS PMO'!$C$93*F21+'ENTRADAS PMO'!$C$99*F22+'ENTRADAS PMO'!$C$104*F23+'ENTRADAS PMO'!$C$106*F24)) -> 19336.3 | G61: =F61+(('ENTRADAS PMO'!$C$18*G10+'ENTRADAS PMO'!$C$24*G11+'ENTRADAS PMO'!$C$33*G12+'ENTRADAS PMO'!$C$36*G13)-('ENTRADAS PMO'!$C$44*G17+'ENTRADAS PMO'!$C$58*G18+'ENTRADAS PMO'!$C$72*G19+'ENTRADAS PMO'!$C$84*G20+'ENTRADAS PMO'!$C$93*G21+'ENTRADAS PMO'!$C$99*G22+'ENTRADAS PMO'!$C$104*G23+'ENTRADAS PMO'!$C$106*G24)) -> 24195.2 | H61: =G61+(('ENTRADAS PMO'!$C$18*H10+'ENTRADAS PMO'!$C$24*H11+'ENTRADAS PMO'!$C$33*H12+'ENTRADAS PMO'!$C$36*H13)-('ENTRADAS PMO'!$C$44*H17+'ENTRADAS PMO'!$C$58*H18+'ENTRADAS PMO'!$C$72*H19+'ENTRADAS PMO'!$C$84*H20+'ENTRADAS PMO'!$C$93*H21+'ENTRADAS PMO'!$C$99*H22+'ENTRADAS PMO'!$C$104*H23+'ENTRADAS PMO'!$C$106*H24)) -> 29054.1 | I61: =H61+(('ENTRADAS PMO'!$C$18*I10+'ENTRADAS PMO'!$C$24*I11+'ENTRADAS PMO'!$C$33*I12+'ENTRADAS PMO'!$C$36*I13)-('ENTRADAS PMO'!$C$44*I17+'ENTRADAS PMO'!$C$58*I18+'ENTRADAS PMO'!$C$72*I19+'ENTRADAS PMO'!$C$84*I20+'ENTRADAS PMO'!$C$93*I21+'ENTRADAS PMO'!$C$99*I22+'ENTRADAS PMO'!$C$104*I23+'ENTRADAS PMO'!$C$106*I24)) -> 33913 | J61: =I61+(('ENTRADAS PMO'!$C$18*J10+'ENTRADAS PMO'!$C$24*J11+'ENTRADAS PMO'!$C$33*J12+'ENTRADAS PMO'!$C$36*J13)-('ENTRADAS PMO'!$C$44*J17+'ENTRADAS PMO'!$C$58*J18+'ENTRADAS PMO'!$C$72*J19+'ENTRADAS PMO'!$C$84*J20+'ENTRADAS PMO'!$C$93*J21+'ENTRADAS PMO'!$C$99*J22+'ENTRADAS PMO'!$C$104*J23+'ENTRADAS PMO'!$C$106*J24)) -> 34100.8 | ... M61: =L61+(('ENTRADAS PMO'!$C$18*M10+'ENTRADAS PMO'!$C$24*M11+'ENTRADAS PMO'!$C$33*M12+'ENTRADAS PMO'!$C$36*M13)-('ENTRADAS PMO'!$C$44*M17+'ENTRADAS PMO'!$C$58*M18+'ENTRADAS PMO'!$C$72*M19+'ENTRADAS PMO'!$C$84*M20+'ENTRADAS PMO'!$C$93*M21+'ENTRADAS PMO'!$C$99*M22+'ENTRADAS PMO'!$C$104*M23+'ENTRADAS PMO'!$C$106*M24)) -> -207591.8
A62: ↳ Necessidade máxima de capital de giro (Conservador) | B62: =MAX(0,-MIN(B61:M61)) -> 207591.8
A64: Base — Saldo acumulado mensal | B64: ='FLUXO DE CAIXA'!$B$5+(('ENTRADAS PMO'!$D$18*B10+'ENTRADAS PMO'!$D$24*B11+'ENTRADAS PMO'!$D$33*B12+'ENTRADAS PMO'!$D$36*B13)-('ENTRADAS PMO'!$D$44*B17+'ENTRADAS PMO'!$D$58*B18+'ENTRADAS PMO'!$D$72*B19+'ENTRADAS PMO'!$D$84*B20+'ENTRADAS PMO'!$D$93*B21+'ENTRADAS PMO'!$D$99*B22+'ENTRADAS PMO'!$D$104*B23+'ENTRADAS PMO'!$D$106*B24)) -> 4120 | C64: =B64+(('ENTRADAS PMO'!$D$18*C10+'ENTRADAS PMO'!$D$24*C11+'ENTRADAS PMO'!$D$33*C12+'ENTRADAS PMO'!$D$36*C13)-('ENTRADAS PMO'!$D$44*C17+'ENTRADAS PMO'!$D$58*C18+'ENTRADAS PMO'!$D$72*C19+'ENTRADAS PMO'!$D$84*C20+'ENTRADAS PMO'!$D$93*C21+'ENTRADAS PMO'!$D$99*C22+'ENTRADAS PMO'!$D$104*C23+'ENTRADAS PMO'!$D$106*C24)) -> -12483.96 | D64: =C64+(('ENTRADAS PMO'!$D$18*D10+'ENTRADAS PMO'!$D$24*D11+'ENTRADAS PMO'!$D$33*D12+'ENTRADAS PMO'!$D$36*D13)-('ENTRADAS PMO'!$D$44*D17+'ENTRADAS PMO'!$D$58*D18+'ENTRADAS PMO'!$D$72*D19+'ENTRADAS PMO'!$D$84*D20+'ENTRADAS PMO'!$D$93*D21+'ENTRADAS PMO'!$D$99*D22+'ENTRADAS PMO'!$D$104*D23+'ENTRADAS PMO'!$D$106*D24)) -> 32188.12 | E64: =D64+(('ENTRADAS PMO'!$D$18*E10+'ENTRADAS PMO'!$D$24*E11+'ENTRADAS PMO'!$D$33*E12+'ENTRADAS PMO'!$D$36*E13)-('ENTRADAS PMO'!$D$44*E17+'ENTRADAS PMO'!$D$58*E18+'ENTRADAS PMO'!$D$72*E19+'ENTRADAS PMO'!$D$84*E20+'ENTRADAS PMO'!$D$93*E21+'ENTRADAS PMO'!$D$99*E22+'ENTRADAS PMO'!$D$104*E23+'ENTRADAS PMO'!$D$106*E24)) -> 76860.2 | F64: =E64+(('ENTRADAS PMO'!$D$18*F10+'ENTRADAS PMO'!$D$24*F11+'ENTRADAS PMO'!$D$33*F12+'ENTRADAS PMO'!$D$36*F13)-('ENTRADAS PMO'!$D$44*F17+'ENTRADAS PMO'!$D$58*F18+'ENTRADAS PMO'!$D$72*F19+'ENTRADAS PMO'!$D$84*F20+'ENTRADAS PMO'!$D$93*F21+'ENTRADAS PMO'!$D$99*F22+'ENTRADAS PMO'!$D$104*F23+'ENTRADAS PMO'!$D$106*F24)) -> 113372.28 | G64: =F64+(('ENTRADAS PMO'!$D$18*G10+'ENTRADAS PMO'!$D$24*G11+'ENTRADAS PMO'!$D$33*G12+'ENTRADAS PMO'!$D$36*G13)-('ENTRADAS PMO'!$D$44*G17+'ENTRADAS PMO'!$D$58*G18+'ENTRADAS PMO'!$D$72*G19+'ENTRADAS PMO'!$D$84*G20+'ENTRADAS PMO'!$D$93*G21+'ENTRADAS PMO'!$D$99*G22+'ENTRADAS PMO'!$D$104*G23+'ENTRADAS PMO'!$D$106*G24)) -> 129608.32 | H64: =G64+(('ENTRADAS PMO'!$D$18*H10+'ENTRADAS PMO'!$D$24*H11+'ENTRADAS PMO'!$D$33*H12+'ENTRADAS PMO'!$D$36*H13)-('ENTRADAS PMO'!$D$44*H17+'ENTRADAS PMO'!$D$58*H18+'ENTRADAS PMO'!$D$72*H19+'ENTRADAS PMO'!$D$84*H20+'ENTRADAS PMO'!$D$93*H21+'ENTRADAS PMO'!$D$99*H22+'ENTRADAS PMO'!$D$104*H23+'ENTRADAS PMO'!$D$106*H24)) -> 145844.36 | I64: =H64+(('ENTRADAS PMO'!$D$18*I10+'ENTRADAS PMO'!$D$24*I11+'ENTRADAS PMO'!$D$33*I12+'ENTRADAS PMO'!$D$36*I13)-('ENTRADAS PMO'!$D$44*I17+'ENTRADAS PMO'!$D$58*I18+'ENTRADAS PMO'!$D$72*I19+'ENTRADAS PMO'!$D$84*I20+'ENTRADAS PMO'!$D$93*I21+'ENTRADAS PMO'!$D$99*I22+'ENTRADAS PMO'!$D$104*I23+'ENTRADAS PMO'!$D$106*I24)) -> 162080.4 | J64: =I64+(('ENTRADAS PMO'!$D$18*J10+'ENTRADAS PMO'!$D$24*J11+'ENTRADAS PMO'!$D$33*J12+'ENTRADAS PMO'!$D$36*J13)-('ENTRADAS PMO'!$D$44*J17+'ENTRADAS PMO'!$D$58*J18+'ENTRADAS PMO'!$D$72*J19+'ENTRADAS PMO'!$D$84*J20+'ENTRADAS PMO'!$D$93*J21+'ENTRADAS PMO'!$D$99*J22+'ENTRADAS PMO'!$D$104*J23+'ENTRADAS PMO'!$D$106*J24)) -> 184092.48 | ... M64: =L64+(('ENTRADAS PMO'!$D$18*M10+'ENTRADAS PMO'!$D$24*M11+'ENTRADAS PMO'!$D$33*M12+'ENTRADAS PMO'!$D$36*M13)-('ENTRADAS PMO'!$D$44*M17+'ENTRADAS PMO'!$D$58*M18+'ENTRADAS PMO'!$D$72*M19+'ENTRADAS PMO'!$D$84*M20+'ENTRADAS PMO'!$D$93*M21+'ENTRADAS PMO'!$D$99*M22+'ENTRADAS PMO'!$D$104*M23+'ENTRADAS PMO'!$D$106*M24)) -> 15231.069
A65: ↳ Necessidade máxima de capital de giro (Base) | B65: =MAX(0,-MIN(B64:M64)) -> 12483.96
A67: Agressivo — Saldo acumulado mensal | B67: ='FLUXO DE CAIXA'!$B$5+(('ENTRADAS PMO'!$E$18*B10+'ENTRADAS PMO'!$E$24*B11+'ENTRADAS PMO'!$E$33*B12+'ENTRADAS PMO'!$E$36*B13)-('ENTRADAS PMO'!$E$44*B17+'ENTRADAS PMO'!$E$58*B18+'ENTRADAS PMO'!$E$72*B19+'ENTRADAS PMO'!$E$84*B20+'ENTRADAS PMO'!$E$93*B21+'ENTRADAS PMO'!$E$99*B22+'ENTRADAS PMO'!$E$104*B23+'ENTRADAS PMO'!$E$106*B24)) -> 10220 | C67: =B67+(('ENTRADAS PMO'!$E$18*C10+'ENTRADAS PMO'!$E$24*C11+'ENTRADAS PMO'!$E$33*C12+'ENTRADAS PMO'!$E$36*C13)-('ENTRADAS PMO'!$E$44*C17+'ENTRADAS PMO'!$E$58*C18+'ENTRADAS PMO'!$E$72*C19+'ENTRADAS PMO'!$E$84*C20+'ENTRADAS PMO'!$E$93*C21+'ENTRADAS PMO'!$E$99*C22+'ENTRADAS PMO'!$E$104*C23+'ENTRADAS PMO'!$E$106*C24)) -> 2398.5 | D67: =C67+(('ENTRADAS PMO'!$E$18*D10+'ENTRADAS PMO'!$E$24*D11+'ENTRADAS PMO'!$E$33*D12+'ENTRADAS PMO'!$E$36*D13)-('ENTRADAS PMO'!$E$44*D17+'ENTRADAS PMO'!$E$58*D18+'ENTRADAS PMO'!$E$72*D19+'ENTRADAS PMO'!$E$84*D20+'ENTRADAS PMO'!$E$93*D21+'ENTRADAS PMO'!$E$99*D22+'ENTRADAS PMO'!$E$104*D23+'ENTRADAS PMO'!$E$106*D24)) -> 70535.5 | E67: =D67+(('ENTRADAS PMO'!$E$18*E10+'ENTRADAS PMO'!$E$24*E11+'ENTRADAS PMO'!$E$33*E12+'ENTRADAS PMO'!$E$36*E13)-('ENTRADAS PMO'!$E$44*E17+'ENTRADAS PMO'!$E$58*E18+'ENTRADAS PMO'!$E$72*E19+'ENTRADAS PMO'!$E$84*E20+'ENTRADAS PMO'!$E$93*E21+'ENTRADAS PMO'!$E$99*E22+'ENTRADAS PMO'!$E$104*E23+'ENTRADAS PMO'!$E$106*E24)) -> 138672.5 | F67: =E67+(('ENTRADAS PMO'!$E$18*F10+'ENTRADAS PMO'!$E$24*F11+'ENTRADAS PMO'!$E$33*F12+'ENTRADAS PMO'!$E$36*F13)-('ENTRADAS PMO'!$E$44*F17+'ENTRADAS PMO'!$E$58*F18+'ENTRADAS PMO'!$E$72*F19+'ENTRADAS PMO'!$E$84*F20+'ENTRADAS PMO'!$E$93*F21+'ENTRADAS PMO'!$E$99*F22+'ENTRADAS PMO'!$E$104*F23+'ENTRADAS PMO'!$E$106*F24)) -> 191639.5 | G67: =F67+(('ENTRADAS PMO'!$E$18*G10+'ENTRADAS PMO'!$E$24*G11+'ENTRADAS PMO'!$E$33*G12+'ENTRADAS PMO'!$E$36*G13)-('ENTRADAS PMO'!$E$44*G17+'ENTRADAS PMO'!$E$58*G18+'ENTRADAS PMO'!$E$72*G19+'ENTRADAS PMO'!$E$84*G20+'ENTRADAS PMO'!$E$93*G21+'ENTRADAS PMO'!$E$99*G22+'ENTRADAS PMO'!$E$104*G23+'ENTRADAS PMO'!$E$106*G24)) -> 215648 | H67: =G67+(('ENTRADAS PMO'!$E$18*H10+'ENTRADAS PMO'!$E$24*H11+'ENTRADAS PMO'!$E$33*H12+'ENTRADAS PMO'!$E$36*H13)-('ENTRADAS PMO'!$E$44*H17+'ENTRADAS PMO'!$E$58*H18+'ENTRADAS PMO'!$E$72*H19+'ENTRADAS PMO'!$E$84*H20+'ENTRADAS PMO'!$E$93*H21+'ENTRADAS PMO'!$E$99*H22+'ENTRADAS PMO'!$E$104*H23+'ENTRADAS PMO'!$E$106*H24)) -> 239656.5 | I67: =H67+(('ENTRADAS PMO'!$E$18*I10+'ENTRADAS PMO'!$E$24*I11+'ENTRADAS PMO'!$E$33*I12+'ENTRADAS PMO'!$E$36*I13)-('ENTRADAS PMO'!$E$44*I17+'ENTRADAS PMO'!$E$58*I18+'ENTRADAS PMO'!$E$72*I19+'ENTRADAS PMO'!$E$84*I20+'ENTRADAS PMO'!$E$93*I21+'ENTRADAS PMO'!$E$99*I22+'ENTRADAS PMO'!$E$104*I23+'ENTRADAS PMO'!$E$106*I24)) -> 263665 | J67: =I67+(('ENTRADAS PMO'!$E$18*J10+'ENTRADAS PMO'!$E$24*J11+'ENTRADAS PMO'!$E$33*J12+'ENTRADAS PMO'!$E$36*J13)-('ENTRADAS PMO'!$E$44*J17+'ENTRADAS PMO'!$E$58*J18+'ENTRADAS PMO'!$E$72*J19+'ENTRADAS PMO'!$E$84*J20+'ENTRADAS PMO'!$E$93*J21+'ENTRADAS PMO'!$E$99*J22+'ENTRADAS PMO'!$E$104*J23+'ENTRADAS PMO'!$E$106*J24)) -> 298632 | ... M67: =L67+(('ENTRADAS PMO'!$E$18*M10+'ENTRADAS PMO'!$E$24*M11+'ENTRADAS PMO'!$E$33*M12+'ENTRADAS PMO'!$E$36*M13)-('ENTRADAS PMO'!$E$44*M17+'ENTRADAS PMO'!$E$58*M18+'ENTRADAS PMO'!$E$72*M19+'ENTRADAS PMO'!$E$84*M20+'ENTRADAS PMO'!$E$93*M21+'ENTRADAS PMO'!$E$99*M22+'ENTRADAS PMO'!$E$104*M23+'ENTRADAS PMO'!$E$106*M24)) -> 118377.33
A68: ↳ Necessidade máxima de capital de giro (Agressivo) | B68: =MAX(0,-MIN(B67:M67)) -> 0

Sheet BREAK-EVEN
A1: PIQUINZADA 2027 | PONTO DE EQUILÍBRIO
A2: Todas as métricas derivam do motor de cálculo (aba Cenarios) e de ENTRADAS PMO.
A4: Indicador | B4: CONSERVADOR | C4: BASE | D4: AGRESSIVO
A5: Ponto de equilíbrio — ingressos SEM patrocínio | B5: =Cenarios!$Q$10 -> 4204.1798 | C5: =Cenarios!$Q$11 -> 3725.0502 | D5: =Cenarios!$Q$12 -> 4163.66
A6: Ponto de equilíbrio — ingressos COM patrocínio esperado | B6: =Cenarios!$R$10 -> 3705.3733 | C6: =Cenarios!$R$11 -> 2730.7544 | D6: =Cenarios!$R$12 -> 2286.8719
A7: Quantidade mínima de ingressos a vender | B7: =Cenarios!$R$10 -> 3705.3733 | C7: =Cenarios!$R$11 -> 2730.7544 | D7: =Cenarios!$R$12 -> 2286.8719
A8: % mínimo de ocupação da capacidade | B8: =Cenarios!$S$10 -> 1.6842606 | C8: =Cenarios!$S$11 -> 0.91025148 | D8: =Cenarios!$S$12 -> 0.65339198
A9: Receita mínima necessária (= Custo Total) | B9: =Cenarios!$K$10 -> 403049.8 | C9: =Cenarios!$K$11 -> 475795.43 | D9: =Cenarios!$K$12 -> 571042.67
A10: Patrocínio mínimo necessário (cobrir o cachê) | B10: =Cenarios!$U$10 -> 160000 | C10: =Cenarios!$U$11 -> 180000 | D10: =Cenarios!$U$12 -> 200000
A11: Margem de segurança (sobre pagantes planejados) | B11: =Cenarios!$T$10 -> -1.4060865 | C11: =Cenarios!$T$11 -> 0.04184055 | D11: =Cenarios!$T$12 -> 0.27400891
A12: Ticket médio mínimo (mantendo demais premissas) | B12: =(Cenarios!$K$10-'ENTRADAS PMO'!$C$24-'ENTRADAS PMO'!$C$33-'ENTRADAS PMO'!$C$36)/Cenarios!$B$10/(1-'ENTRADAS PMO'!$C$13-'ENTRADAS PMO'!$C$14-'ENTRADAS PMO'!$C$15) -> 226.81381 | C12: =(Cenarios!$K$11-'ENTRADAS PMO'!$D$24-'ENTRADAS PMO'!$D$33-'ENTRADAS PMO'!$D$36)/Cenarios!$B$11/(1-'ENTRADAS PMO'!$D$13-'ENTRADAS PMO'!$D$14-'ENTRADAS PMO'!$D$15) -> 100.41561 | D12: =(Cenarios!$K$12-'ENTRADAS PMO'!$E$24-'ENTRADAS PMO'!$E$33-'ENTRADAS PMO'!$E$36)/Cenarios!$B$12/(1-'ENTRADAS PMO'!$E$13-'ENTRADAS PMO'!$E$14-'ENTRADAS PMO'!$E$15) -> 70.183806
A14: SIMULADORES "E SE...?"
A15: Cenário de referência para os simuladores | B15: Base
B16: =IF('BREAK-EVEN'!$B$15="Conservador","C",IF('BREAK-EVEN'!$B$15="Base","D","E")) -> D
A18: 1) Se o patrocínio for R$ ___, quantos ingressos preciso vender?
A19: Patrocínio hipotético (R$) | B19: 100000
A20: → Ingressos necessários | B20: =MAX(0,(INDIRECT("'ENTRADAS PMO'!"&'BREAK-EVEN'!$B$16&"107")-'BREAK-EVEN'!$B$19-INDIRECT("'ENTRADAS PMO'!"&'BREAK-EVEN'!$B$16&"36"))/(INDIRECT("'ENTRADAS PMO'!"&'BREAK-EVEN'!$B$16&"16")*(1-INDIRECT("'ENTRADAS PMO'!"&'BREAK-EVEN'!$B$16&"13")-INDIRECT("'ENTRADAS PMO'!"&'BREAK-EVEN'!$B$16&"14")-INDIRECT("'ENTRADAS PMO'!"&'BREAK-EVEN'!$B$16&"15"))+INDIRECT("'ENTRADAS PMO'!"&'BREAK-EVEN'!$B$16&"30"))) -> 2942.1401
A22: 2) Se eu vender ___ ingressos, quanto de patrocínio preciso?
A23: Ingressos hipotéticos | B23: 2500
A24: → Patrocínio necessário | B24: =MAX(0,INDIRECT("'ENTRADAS PMO'!"&'BREAK-EVEN'!$B$16&"107")-'BREAK-EVEN'!$B$23*(INDIRECT("'ENTRADAS PMO'!"&'BREAK-EVEN'!$B$16&"16")*(1-INDIRECT("'ENTRADAS PMO'!"&'BREAK-EVEN'!$B$16&"13")-INDIRECT("'ENTRADAS PMO'!"&'BREAK-EVEN'!$B$16&"14")-INDIRECT("'ENTRADAS PMO'!"&'BREAK-EVEN'!$B$16&"15"))+INDIRECT("'ENTRADAS PMO'!"&'BREAK-EVEN'!$B$16&"30"))-INDIRECT("'ENTRADAS PMO'!"&'BREAK-EVEN'!$B$16&"36")) -> 156473.94
A26: 3) Se o cachê da atração principal subir para R$ ___, qual o novo break-even?
A27: Novo cachê hipotético (R$) | B27: 220000
A28: → Novo custo total do cenário | B28: =(((INDIRECT("'ENTRADAS PMO'!"&'BREAK-EVEN'!$B$16&"103")-INDIRECT("'ENTRADAS PMO'!"&'BREAK-EVEN'!$B$16&"39")+'BREAK-EVEN'!$B$27)+INDIRECT("'ENTRADAS PMO'!"&'BREAK-EVEN'!$B$16&"104"))*(1+INDIRECT("'ENTRADAS PMO'!"&'BREAK-EVEN'!$B$16&"100"))) -> 518995.43
A29: → Novo break-even (ingressos, com patrocínio esperado) | B29: =MAX(0,((((INDIRECT("'ENTRADAS PMO'!"&'BREAK-EVEN'!$B$16&"103")-INDIRECT("'ENTRADAS PMO'!"&'BREAK-EVEN'!$B$16&"39")+'BREAK-EVEN'!$B$27)+INDIRECT("'ENTRADAS PMO'!"&'BREAK-EVEN'!$B$16&"104"))*(1+INDIRECT("'ENTRADAS PMO'!"&'BREAK-EVEN'!$B$16&"100")))-INDIRECT("'ENTRADAS PMO'!"&'BREAK-EVEN'!$B$16&"24")-INDIRECT("'ENTRADAS PMO'!"&'BREAK-EVEN'!$B$16&"36"))/(INDIRECT("'ENTRADAS PMO'!"&'BREAK-EVEN'!$B$16&"16")*(1-INDIRECT("'ENTRADAS PMO'!"&'BREAK-EVEN'!$B$16&"13")-INDIRECT("'ENTRADAS PMO'!"&'BREAK-EVEN'!$B$16&"14")-INDIRECT("'ENTRADAS PMO'!"&'BREAK-EVEN'!$B$16&"15"))+INDIRECT("'ENTRADAS PMO'!"&'BREAK-EVEN'!$B$16&"30"))) -> 3068.9716
A31: 4) Qual o preço médio mínimo do ingresso para atingir a margem alvo ___?
A32: Margem líquida alvo (%) | B32: 0.1
A33: → Ticket médio mínimo necessário | B33: =IFERROR((INDIRECT("'ENTRADAS PMO'!"&'BREAK-EVEN'!$B$16&"107")/(1-'BREAK-EVEN'!$B$32)-INDIRECT("'ENTRADAS PMO'!"&'BREAK-EVEN'!$B$16&"24")-INDIRECT("'ENTRADAS PMO'!"&'BREAK-EVEN'!$B$16&"33")-INDIRECT("'ENTRADAS PMO'!"&'BREAK-EVEN'!$B$16&"36"))/INDIRECT("'ENTRADAS PMO'!"&'BREAK-EVEN'!$B$16&"8")/(1-INDIRECT("'ENTRADAS PMO'!"&'BREAK-EVEN'!$B$16&"13")-INDIRECT("'ENTRADAS PMO'!"&'BREAK-EVEN'!$B$16&"14")-INDIRECT("'ENTRADAS PMO'!"&'BREAK-EVEN'!$B$16&"15")),0) -> 120.57814

Sheet SENSIBILIDADE
A1: PIQUINZADA 2027 | ANÁLISE DE SENSIBILIDADE
A2: Impacto no RESULTADO do cenário selecionado quando cada variável muda isoladamente (demais premissas mantidas fixas).
A4: Cenário de referência | B4: Base
A5: Coluna do cenário (auto) | B5: =IF(SENSIBILIDADE!$B$4="Conservador","C",IF(SENSIBILIDADE!$B$4="Base","D","E")) -> D
A7: Resultado do cenário (referência) | B7: =INDIRECT("'ENTRADAS PMO'!"&SENSIBILIDADE!$B$5&"18")+INDIRECT("'ENTRADAS PMO'!"&SENSIBILIDADE!$B$5&"33")+INDIRECT("'ENTRADAS PMO'!"&SENSIBILIDADE!$B$5&"24")+INDIRECT("'ENTRADAS PMO'!"&SENSIBILIDADE!$B$5&"36")-INDIRECT("'ENTRADAS PMO'!"&SENSIBILIDADE!$B$5&"107") -> 15231.069
A8: Receita total (referência, base de % de impacto) | B8: =INDIRECT("'ENTRADAS PMO'!"&SENSIBILIDADE!$B$5&"18")+INDIRECT("'ENTRADAS PMO'!"&SENSIBILIDADE!$B$5&"33")+INDIRECT("'ENTRADAS PMO'!"&SENSIBILIDADE!$B$5&"24")+INDIRECT("'ENTRADAS PMO'!"&SENSIBILIDADE!$B$5&"36") -> 491026.5
A10: Variável | B10: -30% | C10: -20% | D10: -10% | E10: BASE | F10: +10% | G10: +20%
A11: Venda de ingressos (qtd. de pagantes) | B11: =(INDIRECT("'ENTRADAS PMO'!"&SENSIBILIDADE!$B$5&"18")*(1+-0.3)+INDIRECT("'ENTRADAS PMO'!"&SENSIBILIDADE!$B$5&"33")*(1+-0.3)+INDIRECT("'ENTRADAS PMO'!"&SENSIBILIDADE!$B$5&"24")+INDIRECT("'ENTRADAS PMO'!"&SENSIBILIDADE!$B$5&"36"))-INDIRECT("'ENTRADAS PMO'!"&SENSIBILIDADE!$B$5&"107") -> -93976.881 | C11: =(INDIRECT("'ENTRADAS PMO'!"&SENSIBILIDADE!$B$5&"18")*(1+-0.2)+INDIRECT("'ENTRADAS PMO'!"&SENSIBILIDADE!$B$5&"33")*(1+-0.2)+INDIRECT("'ENTRADAS PMO'!"&SENSIBILIDADE!$B$5&"24")+INDIRECT("'ENTRADAS PMO'!"&SENSIBILIDADE!$B$5&"36"))-INDIRECT("'ENTRADAS PMO'!"&SENSIBILIDADE!$B$5&"107") -> -57574.231 | D11: =(INDIRECT("'ENTRADAS PMO'!"&SENSIBILIDADE!$B$5&"18")*(1+-0.1)+INDIRECT("'ENTRADAS PMO'!"&SENSIBILIDADE!$B$5&"33")*(1+-0.1)+INDIRECT("'ENTRADAS PMO'!"&SENSIBILIDADE!$B$5&"24")+INDIRECT("'ENTRADAS PMO'!"&SENSIBILIDADE!$B$5&"36"))-INDIRECT("'ENTRADAS PMO'!"&SENSIBILIDADE!$B$5&"107") -> -21171.581 | E11: =(INDIRECT("'ENTRADAS PMO'!"&SENSIBILIDADE!$B$5&"18")*(1+0)+INDIRECT("'ENTRADAS PMO'!"&SENSIBILIDADE!$B$5&"33")*(1+0)+INDIRECT("'ENTRADAS PMO'!"&SENSIBILIDADE!$B$5&"24")+INDIRECT("'ENTRADAS PMO'!"&SENSIBILIDADE!$B$5&"36"))-INDIRECT("'ENTRADAS PMO'!"&SENSIBILIDADE!$B$5&"107") -> 15231.069 | F11: =(INDIRECT("'ENTRADAS PMO'!"&SENSIBILIDADE!$B$5&"18")*(1+0.1)+INDIRECT("'ENTRADAS PMO'!"&SENSIBILIDADE!$B$5&"33")*(1+0.1)+INDIRECT("'ENTRADAS PMO'!"&SENSIBILIDADE!$B$5&"24")+INDIRECT("'ENTRADAS PMO'!"&SENSIBILIDADE!$B$5&"36"))-INDIRECT("'ENTRADAS PMO'!"&SENSIBILIDADE!$B$5&"107") -> 51633.719 | G11: =(INDIRECT("'ENTRADAS PMO'!"&SENSIBILIDADE!$B$5&"18")*(1+0.2)+INDIRECT("'ENTRADAS PMO'!"&SENSIBILIDADE!$B$5&"33")*(1+0.2)+INDIRECT("'ENTRADAS PMO'!"&SENSIBILIDADE!$B$5&"24")+INDIRECT("'ENTRADAS PMO'!"&SENSIBILIDADE!$B$5&"36"))-INDIRECT("'ENTRADAS PMO'!"&SENSIBILIDADE!$B$5&"107") -> 88036.369
A12: Ticket médio | B12: =(INDIRECT("'ENTRADAS PMO'!"&SENSIBILIDADE!$B$5&"18")*(1+-0.3)+INDIRECT("'ENTRADAS PMO'!"&SENSIBILIDADE!$B$5&"33")+INDIRECT("'ENTRADAS PMO'!"&SENSIBILIDADE!$B$5&"24")+INDIRECT("'ENTRADAS PMO'!"&SENSIBILIDADE!$B$5&"36"))-INDIRECT("'ENTRADAS PMO'!"&SENSIBILIDADE!$B$5&"107") -> -68325.171 | C12: =(INDIRECT("'ENTRADAS PMO'!"&SENSIBILIDADE!$B$5&"18")*(1+-0.2)+INDIRECT("'ENTRADAS PMO'!"&SENSIBILIDADE!$B$5&"33")+INDIRECT("'ENTRADAS PMO'!"&SENSIBILIDADE!$B$5&"24")+INDIRECT("'ENTRADAS PMO'!"&SENSIBILIDADE!$B$5&"36"))-INDIRECT("'ENTRADAS PMO'!"&SENSIBILIDADE!$B$5&"107") -> -40473.091 | D12: =(INDIRECT("'ENTRADAS PMO'!"&SENSIBILIDADE!$B$5&"18")*(1+-0.1)+INDIRECT("'ENTRADAS PMO'!"&SENSIBILIDADE!$B$5&"33")+INDIRECT("'ENTRADAS PMO'!"&SENSIBILIDADE!$B$5&"24")+INDIRECT("'ENTRADAS PMO'!"&SENSIBILIDADE!$B$5&"36"))-INDIRECT("'ENTRADAS PMO'!"&SENSIBILIDADE!$B$5&"107") -> -12621.011 | E12: =(INDIRECT("'ENTRADAS PMO'!"&SENSIBILIDADE!$B$5&"18")*(1+0)+INDIRECT("'ENTRADAS PMO'!"&SENSIBILIDADE!$B$5&"33")+INDIRECT("'ENTRADAS PMO'!"&SENSIBILIDADE!$B$5&"24")+INDIRECT("'ENTRADAS PMO'!"&SENSIBILIDADE!$B$5&"36"))-INDIRECT("'ENTRADAS PMO'!"&SENSIBILIDADE!$B$5&"107") -> 15231.069 | F12: =(INDIRECT("'ENTRADAS PMO'!"&SENSIBILIDADE!$B$5&"18")*(1+0.1)+INDIRECT("'ENTRADAS PMO'!"&SENSIBILIDADE!$B$5&"33")+INDIRECT("'ENTRADAS PMO'!"&SENSIBILIDADE!$B$5&"24")+INDIRECT("'ENTRADAS PMO'!"&SENSIBILIDADE!$B$5&"36"))-INDIRECT("'ENTRADAS PMO'!"&SENSIBILIDADE!$B$5&"107") -> 43083.149 | G12: =(INDIRECT("'ENTRADAS PMO'!"&SENSIBILIDADE!$B$5&"18")*(1+0.2)+INDIRECT("'ENTRADAS PMO'!"&SENSIBILIDADE!$B$5&"33")+INDIRECT("'ENTRADAS PMO'!"&SENSIBILIDADE!$B$5&"24")+INDIRECT("'ENTRADAS PMO'!"&SENSIBILIDADE!$B$5&"36"))-INDIRECT("'ENTRADAS PMO'!"&SENSIBILIDADE!$B$5&"107") -> 70935.229
A13: Patrocínio | B13: =(INDIRECT("'ENTRADAS PMO'!"&SENSIBILIDADE!$B$5&"18")+INDIRECT("'ENTRADAS PMO'!"&SENSIBILIDADE!$B$5&"33")+INDIRECT("'ENTRADAS PMO'!"&SENSIBILIDADE!$B$5&"24")*(1+-0.3)+INDIRECT("'ENTRADAS PMO'!"&SENSIBILIDADE!$B$5&"36"))-INDIRECT("'ENTRADAS PMO'!"&SENSIBILIDADE!$B$5&"107") -> -22868.931 | C13: =(INDIRECT("'ENTRADAS PMO'!"&SENSIBILIDADE!$B$5&"18")+INDIRECT("'ENTRADAS PMO'!"&SENSIBILIDADE!$B$5&"33")+INDIRECT("'ENTRADAS PMO'!"&SENSIBILIDADE!$B$5&"24")*(1+-0.2)+INDIRECT("'ENTRADAS PMO'!"&SENSIBILIDADE!$B$5&"36"))-INDIRECT("'ENTRADAS PMO'!"&SENSIBILIDADE!$B$5&"107") -> -10168.931 | D13: =(INDIRECT("'ENTRADAS PMO'!"&SENSIBILIDADE!$B$5&"18")+INDIRECT("'ENTRADAS PMO'!"&SENSIBILIDADE!$B$5&"33")+INDIRECT("'ENTRADAS PMO'!"&SENSIBILIDADE!$B$5&"24")*(1+-0.1)+INDIRECT("'ENTRADAS PMO'!"&SENSIBILIDADE!$B$5&"36"))-INDIRECT("'ENTRADAS PMO'!"&SENSIBILIDADE!$B$5&"107") -> 2531.069 | E13: =(INDIRECT("'ENTRADAS PMO'!"&SENSIBILIDADE!$B$5&"18")+INDIRECT("'ENTRADAS PMO'!"&SENSIBILIDADE!$B$5&"33")+INDIRECT("'ENTRADAS PMO'!"&SENSIBILIDADE!$B$5&"24")*(1+0)+INDIRECT("'ENTRADAS PMO'!"&SENSIBILIDADE!$B$5&"36"))-INDIRECT("'ENTRADAS PMO'!"&SENSIBILIDADE!$B$5&"107") -> 15231.069 | F13: =(INDIRECT("'ENTRADAS PMO'!"&SENSIBILIDADE!$B$5&"18")+INDIRECT("'ENTRADAS PMO'!"&SENSIBILIDADE!$B$5&"33")+INDIRECT("'ENTRADAS PMO'!"&SENSIBILIDADE!$B$5&"24")*(1+0.1)+INDIRECT("'ENTRADAS PMO'!"&SENSIBILIDADE!$B$5&"36"))-INDIRECT("'ENTRADAS PMO'!"&SENSIBILIDADE!$B$5&"107") -> 27931.069 | G13: =(INDIRECT("'ENTRADAS PMO'!"&SENSIBILIDADE!$B$5&"18")+INDIRECT("'ENTRADAS PMO'!"&SENSIBILIDADE!$B$5&"33")+INDIRECT("'ENTRADAS PMO'!"&SENSIBILIDADE!$B$5&"24")*(1+0.2)+INDIRECT("'ENTRADAS PMO'!"&SENSIBILIDADE!$B$5&"36"))-INDIRECT("'ENTRADAS PMO'!"&SENSIBILIDADE!$B$5&"107") -> 40631.069
A14: Cachê da atração principal | B14: =(INDIRECT("'ENTRADAS PMO'!"&SENSIBILIDADE!$B$5&"18")+INDIRECT("'ENTRADAS PMO'!"&SENSIBILIDADE!$B$5&"33")+INDIRECT("'ENTRADAS PMO'!"&SENSIBILIDADE!$B$5&"24")+INDIRECT("'ENTRADAS PMO'!"&SENSIBILIDADE!$B$5&"36"))-(((INDIRECT("'ENTRADAS PMO'!"&SENSIBILIDADE!$B$5&"103")+INDIRECT("'ENTRADAS PMO'!"&SENSIBILIDADE!$B$5&"39")*((1+-0.3)-1))+INDIRECT("'ENTRADAS PMO'!"&SENSIBILIDADE!$B$5&"104"))*(1+INDIRECT("'ENTRADAS PMO'!"&SENSIBILIDADE!$B$5&"100"))) -> 73551.069 | C14: =(INDIRECT("'ENTRADAS PMO'!"&SENSIBILIDADE!$B$5&"18")+INDIRECT("'ENTRADAS PMO'!"&SENSIBILIDADE!$B$5&"33")+INDIRECT("'ENTRADAS PMO'!"&SENSIBILIDADE!$B$5&"24")+INDIRECT("'ENTRADAS PMO'!"&SENSIBILIDADE!$B$5&"36"))-(((INDIRECT("'ENTRADAS PMO'!"&SENSIBILIDADE!$B$5&"103")+INDIRECT("'ENTRADAS PMO'!"&SENSIBILIDADE!$B$5&"39")*((1+-0.2)-1))+INDIRECT("'ENTRADAS PMO'!"&SENSIBILIDADE!$B$5&"104"))*(1+INDIRECT("'ENTRADAS PMO'!"&SENSIBILIDADE!$B$5&"100"))) -> 54111.069 | D14: =(INDIRECT("'ENTRADAS PMO'!"&SENSIBILIDADE!$B$5&"18")+INDIRECT("'ENTRADAS PMO'!"&SENSIBILIDADE!$B$5&"33")+INDIRECT("'ENTRADAS PMO'!"&SENSIBILIDADE!$B$5&"24")+INDIRECT("'ENTRADAS PMO'!"&SENSIBILIDADE!$B$5&"36"))-(((INDIRECT("'ENTRADAS PMO'!"&SENSIBILIDADE!$B$5&"103")+INDIRECT("'ENTRADAS PMO'!"&SENSIBILIDADE!$B$5&"39")*((1+-0.1)-1))+INDIRECT("'ENTRADAS PMO'!"&SENSIBILIDADE!$B$5&"104"))*(1+INDIRECT("'ENTRADAS PMO'!"&SENSIBILIDADE!$B$5&"100"))) -> 34671.069 | E14: =(INDIRECT("'ENTRADAS PMO'!"&SENSIBILIDADE!$B$5&"18")+INDIRECT("'ENTRADAS PMO'!"&SENSIBILIDADE!$B$5&"33")+INDIRECT("'ENTRADAS PMO'!"&SENSIBILIDADE!$B$5&"24")+INDIRECT("'ENTRADAS PMO'!"&SENSIBILIDADE!$B$5&"36"))-(((INDIRECT("'ENTRADAS PMO'!"&SENSIBILIDADE!$B$5&"103")+INDIRECT("'ENTRADAS PMO'!"&SENSIBILIDADE!$B$5&"39")*((1+0)-1))+INDIRECT("'ENTRADAS PMO'!"&SENSIBILIDADE!$B$5&"104"))*(1+INDIRECT("'ENTRADAS PMO'!"&SENSIBILIDADE!$B$5&"100"))) -> 15231.069 | F14: =(INDIRECT("'ENTRADAS PMO'!"&SENSIBILIDADE!$B$5&"18")+INDIRECT("'ENTRADAS PMO'!"&SENSIBILIDADE!$B$5&"33")+INDIRECT("'ENTRADAS PMO'!"&SENSIBILIDADE!$B$5&"24")+INDIRECT("'ENTRADAS PMO'!"&SENSIBILIDADE!$B$5&"36"))-(((INDIRECT("'ENTRADAS PMO'!"&SENSIBILIDADE!$B$5&"103")+INDIRECT("'ENTRADAS PMO'!"&SENSIBILIDADE!$B$5&"39")*((1+0.1)-1))+INDIRECT("'ENTRADAS PMO'!"&SENSIBILIDADE!$B$5&"104"))*(1+INDIRECT("'ENTRADAS PMO'!"&SENSIBILIDADE!$B$5&"100"))) -> -4208.931 | G14: =(INDIRECT("'ENTRADAS PMO'!"&SENSIBILIDADE!$B$5&"18")+INDIRECT("'ENTRADAS PMO'!"&SENSIBILIDADE!$B$5&"33")+INDIRECT("'ENTRADAS PMO'!"&SENSIBILIDADE!$B$5&"24")+INDIRECT("'ENTRADAS PMO'!"&SENSIBILIDADE!$B$5&"36"))-(((INDIRECT("'ENTRADAS PMO'!"&SENSIBILIDADE!$B$5&"103")+INDIRECT("'ENTRADAS PMO'!"&SENSIBILIDADE!$B$5&"39")*((1+0.2)-1))+INDIRECT("'ENTRADAS PMO'!"&SENSIBILIDADE!$B$5&"104"))*(1+INDIRECT("'ENTRADAS PMO'!"&SENSIBILIDADE!$B$5&"100"))) -> -23648.931
A15: Custos de estrutura | B15: =(INDIRECT("'ENTRADAS PMO'!"&SENSIBILIDADE!$B$5&"18")+INDIRECT("'ENTRADAS PMO'!"&SENSIBILIDADE!$B$5&"33")+INDIRECT("'ENTRADAS PMO'!"&SENSIBILIDADE!$B$5&"24")+INDIRECT("'ENTRADAS PMO'!"&SENSIBILIDADE!$B$5&"36"))-(((INDIRECT("'ENTRADAS PMO'!"&SENSIBILIDADE!$B$5&"103")+INDIRECT("'ENTRADAS PMO'!"&SENSIBILIDADE!$B$5&"58")*((1+-0.3)-1))+INDIRECT("'ENTRADAS PMO'!"&SENSIBILIDADE!$B$5&"104"))*(1+INDIRECT("'ENTRADAS PMO'!"&SENSIBILIDADE!$B$5&"100"))) -> 44391.069 | C15: =(INDIRECT("'ENTRADAS PMO'!"&SENSIBILIDADE!$B$5&"18")+INDIRECT("'ENTRADAS PMO'!"&SENSIBILIDADE!$B$5&"33")+INDIRECT("'ENTRADAS PMO'!"&SENSIBILIDADE!$B$5&"24")+INDIRECT("'ENTRADAS PMO'!"&SENSIBILIDADE!$B$5&"36"))-(((INDIRECT("'ENTRADAS PMO'!"&SENSIBILIDADE!$B$5&"103")+INDIRECT("'ENTRADAS PMO'!"&SENSIBILIDADE!$B$5&"58")*((1+-0.2)-1))+INDIRECT("'ENTRADAS PMO'!"&SENSIBILIDADE!$B$5&"104"))*(1+INDIRECT("'ENTRADAS PMO'!"&SENSIBILIDADE!$B$5&"100"))) -> 34671.069 | D15: =(INDIRECT("'ENTRADAS PMO'!"&SENSIBILIDADE!$B$5&"18")+INDIRECT("'ENTRADAS PMO'!"&SENSIBILIDADE!$B$5&"33")+INDIRECT("'ENTRADAS PMO'!"&SENSIBILIDADE!$B$5&"24")+INDIRECT("'ENTRADAS PMO'!"&SENSIBILIDADE!$B$5&"36"))-(((INDIRECT("'ENTRADAS PMO'!"&SENSIBILIDADE!$B$5&"103")+INDIRECT("'ENTRADAS PMO'!"&SENSIBILIDADE!$B$5&"58")*((1+-0.1)-1))+INDIRECT("'ENTRADAS PMO'!"&SENSIBILIDADE!$B$5&"104"))*(1+INDIRECT("'ENTRADAS PMO'!"&SENSIBILIDADE!$B$5&"100"))) -> 24951.069 | E15: =(INDIRECT("'ENTRADAS PMO'!"&SENSIBILIDADE!$B$5&"18")+INDIRECT("'ENTRADAS PMO'!"&SENSIBILIDADE!$B$5&"33")+INDIRECT("'ENTRADAS PMO'!"&SENSIBILIDADE!$B$5&"24")+INDIRECT("'ENTRADAS PMO'!"&SENSIBILIDADE!$B$5&"36"))-(((INDIRECT("'ENTRADAS PMO'!"&SENSIBILIDADE!$B$5&"103")+INDIRECT("'ENTRADAS PMO'!"&SENSIBILIDADE!$B$5&"58")*((1+0)-1))+INDIRECT("'ENTRADAS PMO'!"&SENSIBILIDADE!$B$5&"104"))*(1+INDIRECT("'ENTRADAS PMO'!"&SENSIBILIDADE!$B$5&"100"))) -> 15231.069 | F15: =(INDIRECT("'ENTRADAS PMO'!"&SENSIBILIDADE!$B$5&"18")+INDIRECT("'ENTRADAS PMO'!"&SENSIBILIDADE!$B$5&"33")+INDIRECT("'ENTRADAS PMO'!"&SENSIBILIDADE!$B$5&"24")+INDIRECT("'ENTRADAS PMO'!"&SENSIBILIDADE!$B$5&"36"))-(((INDIRECT("'ENTRADAS PMO'!"&SENSIBILIDADE!$B$5&"103")+INDIRECT("'ENTRADAS PMO'!"&SENSIBILIDADE!$B$5&"58")*((1+0.1)-1))+INDIRECT("'ENTRADAS PMO'!"&SENSIBILIDADE!$B$5&"104"))*(1+INDIRECT("'ENTRADAS PMO'!"&SENSIBILIDADE!$B$5&"100"))) -> 5511.069 | G15: =(INDIRECT("'ENTRADAS PMO'!"&SENSIBILIDADE!$B$5&"18")+INDIRECT("'ENTRADAS PMO'!"&SENSIBILIDADE!$B$5&"33")+INDIRECT("'ENTRADAS PMO'!"&SENSIBILIDADE!$B$5&"24")+INDIRECT("'ENTRADAS PMO'!"&SENSIBILIDADE!$B$5&"36"))-(((INDIRECT("'ENTRADAS PMO'!"&SENSIBILIDADE!$B$5&"103")+INDIRECT("'ENTRADAS PMO'!"&SENSIBILIDADE!$B$5&"58")*((1+0.2)-1))+INDIRECT("'ENTRADAS PMO'!"&SENSIBILIDADE!$B$5&"104"))*(1+INDIRECT("'ENTRADAS PMO'!"&SENSIBILIDADE!$B$5&"100"))) -> -4208.931
A16: Custos gerais (custo total) | B16: =(INDIRECT("'ENTRADAS PMO'!"&SENSIBILIDADE!$B$5&"18")+INDIRECT("'ENTRADAS PMO'!"&SENSIBILIDADE!$B$5&"33")+INDIRECT("'ENTRADAS PMO'!"&SENSIBILIDADE!$B$5&"24")+INDIRECT("'ENTRADAS PMO'!"&SENSIBILIDADE!$B$5&"36"))-INDIRECT("'ENTRADAS PMO'!"&SENSIBILIDADE!$B$5&"107")*(1+-0.3) -> 157969.7 | C16: =(INDIRECT("'ENTRADAS PMO'!"&SENSIBILIDADE!$B$5&"18")+INDIRECT("'ENTRADAS PMO'!"&SENSIBILIDADE!$B$5&"33")+INDIRECT("'ENTRADAS PMO'!"&SENSIBILIDADE!$B$5&"24")+INDIRECT("'ENTRADAS PMO'!"&SENSIBILIDADE!$B$5&"36"))-INDIRECT("'ENTRADAS PMO'!"&SENSIBILIDADE!$B$5&"107")*(1+-0.2) -> 110390.16 | D16: =(INDIRECT("'ENTRADAS PMO'!"&SENSIBILIDADE!$B$5&"18")+INDIRECT("'ENTRADAS PMO'!"&SENSIBILIDADE!$B$5&"33")+INDIRECT("'ENTRADAS PMO'!"&SENSIBILIDADE!$B$5&"24")+INDIRECT("'ENTRADAS PMO'!"&SENSIBILIDADE!$B$5&"36"))-INDIRECT("'ENTRADAS PMO'!"&SENSIBILIDADE!$B$5&"107")*(1+-0.1) -> 62810.612 | E16: =(INDIRECT("'ENTRADAS PMO'!"&SENSIBILIDADE!$B$5&"18")+INDIRECT("'ENTRADAS PMO'!"&SENSIBILIDADE!$B$5&"33")+INDIRECT("'ENTRADAS PMO'!"&SENSIBILIDADE!$B$5&"24")+INDIRECT("'ENTRADAS PMO'!"&SENSIBILIDADE!$B$5&"36"))-INDIRECT("'ENTRADAS PMO'!"&SENSIBILIDADE!$B$5&"107")*(1+0) -> 15231.069 | F16: =(INDIRECT("'ENTRADAS PMO'!"&SENSIBILIDADE!$B$5&"18")+INDIRECT("'ENTRADAS PMO'!"&SENSIBILIDADE!$B$5&"33")+INDIRECT("'ENTRADAS PMO'!"&SENSIBILIDADE!$B$5&"24")+INDIRECT("'ENTRADAS PMO'!"&SENSIBILIDADE!$B$5&"36"))-INDIRECT("'ENTRADAS PMO'!"&SENSIBILIDADE!$B$5&"107")*(1+0.1) -> -32348.474 | G16: =(INDIRECT("'ENTRADAS PMO'!"&SENSIBILIDADE!$B$5&"18")+INDIRECT("'ENTRADAS PMO'!"&SENSIBILIDADE!$B$5&"33")+INDIRECT("'ENTRADAS PMO'!"&SENSIBILIDADE!$B$5&"24")+INDIRECT("'ENTRADAS PMO'!"&SENSIBILIDADE!$B$5&"36"))-INDIRECT("'ENTRADAS PMO'!"&SENSIBILIDADE!$B$5&"107")*(1+0.2) -> -79928.017
A17: Consumo por participante | B17: =(INDIRECT("'ENTRADAS PMO'!"&SENSIBILIDADE!$B$5&"18")+INDIRECT("'ENTRADAS PMO'!"&SENSIBILIDADE!$B$5&"33")*(1+-0.3)+INDIRECT("'ENTRADAS PMO'!"&SENSIBILIDADE!$B$5&"24")+INDIRECT("'ENTRADAS PMO'!"&SENSIBILIDADE!$B$5&"36"))-INDIRECT("'ENTRADAS PMO'!"&SENSIBILIDADE!$B$5&"107") -> -10420.641 | C17: =(INDIRECT("'ENTRADAS PMO'!"&SENSIBILIDADE!$B$5&"18")+INDIRECT("'ENTRADAS PMO'!"&SENSIBILIDADE!$B$5&"33")*(1+-0.2)+INDIRECT("'ENTRADAS PMO'!"&SENSIBILIDADE!$B$5&"24")+INDIRECT("'ENTRADAS PMO'!"&SENSIBILIDADE!$B$5&"36"))-INDIRECT("'ENTRADAS PMO'!"&SENSIBILIDADE!$B$5&"107") -> -1870.071 | D17: =(INDIRECT("'ENTRADAS PMO'!"&SENSIBILIDADE!$B$5&"18")+INDIRECT("'ENTRADAS PMO'!"&SENSIBILIDADE!$B$5&"33")*(1+-0.1)+INDIRECT("'ENTRADAS PMO'!"&SENSIBILIDADE!$B$5&"24")+INDIRECT("'ENTRADAS PMO'!"&SENSIBILIDADE!$B$5&"36"))-INDIRECT("'ENTRADAS PMO'!"&SENSIBILIDADE!$B$5&"107") -> 6680.499 | E17: =(INDIRECT("'ENTRADAS PMO'!"&SENSIBILIDADE!$B$5&"18")+INDIRECT("'ENTRADAS PMO'!"&SENSIBILIDADE!$B$5&"33")*(1+0)+INDIRECT("'ENTRADAS PMO'!"&SENSIBILIDADE!$B$5&"24")+INDIRECT("'ENTRADAS PMO'!"&SENSIBILIDADE!$B$5&"36"))-INDIRECT("'ENTRADAS PMO'!"&SENSIBILIDADE!$B$5&"107") -> 15231.069 | F17: =(INDIRECT("'ENTRADAS PMO'!"&SENSIBILIDADE!$B$5&"18")+INDIRECT("'ENTRADAS PMO'!"&SENSIBILIDADE!$B$5&"33")*(1+0.1)+INDIRECT("'ENTRADAS PMO'!"&SENSIBILIDADE!$B$5&"24")+INDIRECT("'ENTRADAS PMO'!"&SENSIBILIDADE!$B$5&"36"))-INDIRECT("'ENTRADAS PMO'!"&SENSIBILIDADE!$B$5&"107") -> 23781.639 | G17: =(INDIRECT("'ENTRADAS PMO'!"&SENSIBILIDADE!$B$5&"18")+INDIRECT("'ENTRADAS PMO'!"&SENSIBILIDADE!$B$5&"33")*(1+0.2)+INDIRECT("'ENTRADAS PMO'!"&SENSIBILIDADE!$B$5&"24")+INDIRECT("'ENTRADAS PMO'!"&SENSIBILIDADE!$B$5&"36"))-INDIRECT("'ENTRADAS PMO'!"&SENSIBILIDADE!$B$5&"107") -> 32332.209
A19: RANKING DE IMPACTO (variação de referência: ±20%)
A20: Variável | B20: Variação testada | C20: Impacto no resultado (R$) | D20: Impacto (% da receita) | E20: Nível de sensibilidade | G20: Ranking | I20: Faixas (editável)
A21: Venda de ingressos (qtd. de pagantes) | B21: +20% / -20% | C21: =MAX(ABS(C11-E11),ABS(F11-E11)) -> 72805.3 | D21: =IFERROR(C21/SENSIBILIDADE!$B$8,0) -> 0.14827163 | E21: =IF(D21<SENSIBILIDADE!$J$21,"Baixo",IF(D21<SENSIBILIDADE!$J$22,"Moderado",IF(D21<SENSIBILIDADE!$J$23,"Alto","Crítico"))) -> Moderado | G21: =RANK(C21,$C$21:$C$27) -> 2 | I21: Baixo: < | J21: 0.05
A22: Ticket médio | B22: +20% / -20% | C22: =MAX(ABS(C12-E12),ABS(F12-E12)) -> 55704.16 | D22: =IFERROR(C22/SENSIBILIDADE!$B$8,0) -> 0.1134443 | E22: =IF(D22<SENSIBILIDADE!$J$21,"Baixo",IF(D22<SENSIBILIDADE!$J$22,"Moderado",IF(D22<SENSIBILIDADE!$J$23,"Alto","Crítico"))) -> Moderado | G22: =RANK(C22,$C$21:$C$27) -> 3 | I22: Moderado: < | J22: 0.15
A23: Patrocínio | B23: +20% / -20% | C23: =MAX(ABS(C13-E13),ABS(F13-E13)) -> 25400 | D23: =IFERROR(C23/SENSIBILIDADE!$B$8,0) -> 0.051728369 | E23: =IF(D23<SENSIBILIDADE!$J$21,"Baixo",IF(D23<SENSIBILIDADE!$J$22,"Moderado",IF(D23<SENSIBILIDADE!$J$23,"Alto","Crítico"))) -> Moderado | G23: =RANK(C23,$C$21:$C$27) -> 5 | I23: Alto: < | J23: 0.3
A24: Cachê da atração principal | B24: +20% / -20% | C24: =MAX(ABS(C14-E14),ABS(F14-E14)) -> 38880 | D24: =IFERROR(C24/SENSIBILIDADE!$B$8,0) -> 0.079181063 | E24: =IF(D24<SENSIBILIDADE!$J$21,"Baixo",IF(D24<SENSIBILIDADE!$J$22,"Moderado",IF(D24<SENSIBILIDADE!$J$23,"Alto","Crítico"))) -> Moderado | G24: =RANK(C24,$C$21:$C$27) -> 4
A25: Custos de estrutura | B25: +20% / -20% | C25: =MAX(ABS(C15-E15),ABS(F15-E15)) -> 19440 | D25: =IFERROR(C25/SENSIBILIDADE!$B$8,0) -> 0.039590531 | E25: =IF(D25<SENSIBILIDADE!$J$21,"Baixo",IF(D25<SENSIBILIDADE!$J$22,"Moderado",IF(D25<SENSIBILIDADE!$J$23,"Alto","Crítico"))) -> Baixo | G25: =RANK(C25,$C$21:$C$27) -> 6
A26: Custos gerais (custo total) | B26: +20% / -20% | C26: =MAX(ABS(C16-E16),ABS(F16-E16)) -> 95159.086 | D26: =IFERROR(C26/SENSIBILIDADE!$B$8,0) -> 0.19379623 | E26: =IF(D26<SENSIBILIDADE!$J$21,"Baixo",IF(D26<SENSIBILIDADE!$J$22,"Moderado",IF(D26<SENSIBILIDADE!$J$23,"Alto","Crítico"))) -> Alto | G26: =RANK(C26,$C$21:$C$27) -> 1
A27: Consumo por participante | B27: +20% / -20% | C27: =MAX(ABS(C17-E17),ABS(F17-E17)) -> 17101.14 | D27: =IFERROR(C27/SENSIBILIDADE!$B$8,0) -> 0.034827326 | E27: =IF(D27<SENSIBILIDADE!$J$21,"Baixo",IF(D27<SENSIBILIDADE!$J$22,"Moderado",IF(D27<SENSIBILIDADE!$J$23,"Alto","Crítico"))) -> Baixo | G27: =RANK(C27,$C$21:$C$27) -> 7

Sheet RISCOS
A1: PIQUINZADA 2027 | GESTÃO DE RISCOS (RISK REGISTER)
A2: Probabilidade e Impacto em escala de 1 (muito baixo) a 5 (muito alto). Score = Probabilidade × Impacto.
A4: ID | B4: Categoria | C4: Risco | D4: Causa | E4: Consequência | F4: Probabilidade (1-5) | G4: Impacto (1-5) | H4: Score | I4: Classificação | J4: Resposta ao risco | K4: Plano de mitigação | L4: Responsável | M4: Prazo | N4: Status | O4: Score eficaz (priorização, exclui encerrados)
A5: 1 | B5: Financeiro | C5: Déficit de caixa antes do evento | D5: Concentração de custos (sinais/cachês) no início do cronograma | E5: Necessidade de aporte emergencial ou atraso de pagamentos | F5: 3 | G5: 4 | H5: =F5*G5 -> 12 | I5: =IF(H5>=16,"Crítico",IF(H5>=10,"Alto",IF(H5>=5,"Moderado","Baixo"))) -> Alto | J5: Mitigar | K5: Negociar prazos de pagamento e escalonar sinais; manter linha de crédito de contingência | L5: Produção | N5: Aberto | O5: =IF(N5="Encerrado",-1,H5) -> 12
A6: 2 | B6: Financeiro | C6: Estouro do orçamento aprovado (BAC) | D6: Reestimativas subdimensionadas em itens de estrutura/produção | E6: Redução da margem ou necessidade de patrocínio extra | F6: 3 | G6: 3 | H6: =F6*G6 -> 9 | I6: =IF(H6>=16,"Crítico",IF(H6>=10,"Alto",IF(H6>=5,"Moderado","Baixo"))) -> Moderado | J6: Mitigar | K6: Acompanhar EAC semanalmente na aba CUSTOS; travar reserva de contingência | L6: Produção | N6: Aberto | O6: =IF(N6="Encerrado",-1,H6) -> 9
A7: 3 | B7: Comercial | C7: Baixa velocidade de vendas de ingressos | D7: Concorrência de eventos na mesma data/região | E7: Meta de pagantes não atingida, pressão sobre break-even | F7: 3 | G7: 4 | H7: =F7*G7 -> 12 | I7: =IF(H7>=16,"Crítico",IF(H7>=10,"Alto",IF(H7>=5,"Moderado","Baixo"))) -> Alto | J7: Mitigar | K7: Reforçar campanha de tráfego pago e ação de lotes promocionais | L7: Produção | N7: Aberto | O7: =IF(N7="Encerrado",-1,H7) -> 12
A8: 4 | B8: Ingressos | C8: Excesso de cortesias/permutas | D8: Falta de política formal de cortesias | E8: Redução da receita líquida de bilheteria | F8: 2 | G8: 3 | H8: =F8*G8 -> 6 | I8: =IF(H8>=16,"Crítico",IF(H8>=10,"Alto",IF(H8>=5,"Moderado","Baixo"))) -> Moderado | J8: Mitigar | K8: Definir e aprovar limite máximo de cortesias por área | L8: Produção | N8: Aberto | O8: =IF(N8="Encerrado",-1,H8) -> 6
A9: 5 | B9: Patrocínio | C9: Não fechamento das cotas em negociação | D9: Ciclo de decisão do patrocinador mais longo que o cronograma do evento | E9: Cobertura do cachê principal comprometida | F9: 4 | G9: 5 | H9: =F9*G9 -> 20 | I9: =IF(H9>=16,"Crítico",IF(H9>=10,"Alto",IF(H9>=5,"Moderado","Baixo"))) -> Crítico | J9: Mitigar | K9: Priorizar pipeline com follow-up semanal; ter plano B de cotas menores | L9: Produção | N9: Aberto | O9: =IF(N9="Encerrado",-1,H9) -> 20
A10: 6 | B10: Patrocínio | C10: Inadimplência de patrocinador contratado | D10: Fragilidade financeira do patrocinador | E10: Receita esperada não realizada | F10: 2 | G10: 4 | H10: =F10*G10 -> 8 | I10: =IF(H10>=16,"Crítico",IF(H10>=10,"Alto",IF(H10>=5,"Moderado","Baixo"))) -> Moderado | J10: Transferir | K10: Formalizar contrato com sinal e garantias; nota fiscal antecipada | L10: Produção | N10: Aberto | O10: =IF(N10="Encerrado",-1,H10) -> 8
A11: 7 | B11: Artista | C11: Cancelamento da atração principal | D11: Agenda do artista, motivos de saúde ou força maior | E11: Reformulação total do line-up e possível cancelamento do evento | F11: 2 | G11: 5 | H11: =F11*G11 -> 10 | I11: =IF(H11>=16,"Crítico",IF(H11>=10,"Alto",IF(H11>=5,"Moderado","Baixo"))) -> Alto | J11: Mitigar | K11: Cláusula contratual de contingência e seguro de cancelamento | L11: Produção | N11: Aberto | O11: =IF(N11="Encerrado",-1,H11) -> 10
A12: 8 | B12: Artista | C12: Aumento do cachê em renegociação | D12: Alta demanda de mercado pela atração | E12: Piora do break-even e da margem | F12: 2 | G12: 3 | H12: =F12*G12 -> 6 | I12: =IF(H12>=16,"Crítico",IF(H12>=10,"Alto",IF(H12>=5,"Moderado","Baixo"))) -> Moderado | J12: Aceitar | K12: Fechar contrato com valor travado o quanto antes (ver GATE 2) | L12: Produção | N12: Aberto | O12: =IF(N12="Encerrado",-1,H12) -> 6
A13: 9 | B13: Fornecedor | C13: Fornecedor-chave (estrutura/som) não entrega | D13: Concentração em fornecedor único, sem plano B | E13: Impacto direto na qualidade e segurança do evento | F13: 2 | G13: 4 | H13: =F13*G13 -> 8 | I13: =IF(H13>=16,"Crítico",IF(H13>=10,"Alto",IF(H13>=5,"Moderado","Baixo"))) -> Moderado | J13: Mitigar | K13: Contratar fornecedor backup e prever multas contratuais | L13: Produção | N13: Aberto | O13: =IF(N13="Encerrado",-1,H13) -> 8
A14: 10 | B14: Infraestrutura | C14: Falha estrutural (palco/gradil/energia) | D14: Montagem fora do padrão técnico ou fiscalização insuficiente | E14: Risco à segurança do público e possível interdição | F14: 2 | G14: 5 | H14: =F14*G14 -> 10 | I14: =IF(H14>=16,"Crítico",IF(H14>=10,"Alto",IF(H14>=5,"Moderado","Baixo"))) -> Alto | J14: Mitigar | K14: Laudo técnico (ART) obrigatório e vistoria antes da abertura dos portões | L14: Produção | N14: Aberto | O14: =IF(N14="Encerrado",-1,H14) -> 10
A15: 11 | B15: Segurança | C15: Incidente de segurança/tumulto | D15: Efetivo de segurança subdimensionado para o público | E15: Risco à integridade física e exposição jurídica/reputacional | F15: 2 | G15: 5 | H15: =F15*G15 -> 10 | I15: =IF(H15>=16,"Crítico",IF(H15>=10,"Alto",IF(H15>=5,"Moderado","Baixo"))) -> Alto | J15: Mitigar | K15: Dimensionar segurança conforme normas e plano de emergência | L15: Produção | N15: Aberto | O15: =IF(N15="Encerrado",-1,H15) -> 10
A16: 12 | B16: Licenciamento | C16: Atraso ou negativa de alvará/licença | D16: Documentação incompleta ou prazo apertado junto ao órgão público | E16: Risco de cancelamento ou adiamento do evento | F16: 2 | G16: 5 | H16: =F16*G16 -> 10 | I16: =IF(H16>=16,"Crítico",IF(H16>=10,"Alto",IF(H16>=5,"Moderado","Baixo"))) -> Alto | J16: Mitigar | K16: Iniciar processo de licenciamento com folga mínima de 90 dias | L16: Produção | N16: Aberto | O16: =IF(N16="Encerrado",-1,H16) -> 10
... A20: 16 | B20: Operação | C20: Acidente de trabalho na montagem/desmontagem | D20: Prazos apertados e equipe terceirizada sem treinamento | E20: Risco jurídico, atraso no cronograma físico | F20: 2 | G20: 4 | H20: =F20*G20 -> 8 | I20: =IF(H20>=16,"Crítico",IF(H20>=10,"Alto",IF(H20>=5,"Moderado","Baixo"))) -> Moderado | J20: Mitigar | K20: Exigir NRs e treinamento de segurança de todos os fornecedores | L20: Produção | N20: Aberto | O20: =IF(N20="Encerrado",-1,H20) -> 8
A23: MAPA DE CALOR — PROBABILIDADE × IMPACTO (contagem de riscos)
A24: Prob. \ Impacto | B24: 1 | C24: 2 | D24: 3 | E24: 4 | F24: 5
A25: 5 | B25: =COUNTIFS($F$5:$F$20,5,$G$5:$G$20,1) -> 0 | C25: =COUNTIFS($F$5:$F$20,5,$G$5:$G$20,2) -> 0 | D25: =COUNTIFS($F$5:$F$20,5,$G$5:$G$20,3) -> 0 | E25: =COUNTIFS($F$5:$F$20,5,$G$5:$G$20,4) -> 0 | F25: =COUNTIFS($F$5:$F$20,5,$G$5:$G$20,5) -> 0
A26: 4 | B26: =COUNTIFS($F$5:$F$20,4,$G$5:$G$20,1) -> 0 | C26: =COUNTIFS($F$5:$F$20,4,$G$5:$G$20,2) -> 0 | D26: =COUNTIFS($F$5:$F$20,4,$G$5:$G$20,3) -> 0 | E26: =COUNTIFS($F$5:$F$20,4,$G$5:$G$20,4) -> 0 | F26: =COUNTIFS($F$5:$F$20,4,$G$5:$G$20,5) -> 1
A27: 3 | B27: =COUNTIFS($F$5:$F$20,3,$G$5:$G$20,1) -> 0 | C27: =COUNTIFS($F$5:$F$20,3,$G$5:$G$20,2) -> 1 | D27: =COUNTIFS($F$5:$F$20,3,$G$5:$G$20,3) -> 3 | E27: =COUNTIFS($F$5:$F$20,3,$G$5:$G$20,4) -> 2 | F27: =COUNTIFS($F$5:$F$20,3,$G$5:$G$20,5) -> 0
A28: 2 | B28: =COUNTIFS($F$5:$F$20,2,$G$5:$G$20,1) -> 0 | C28: =COUNTIFS($F$5:$F$20,2,$G$5:$G$20,2) -> 0 | D28: =COUNTIFS($F$5:$F$20,2,$G$5:$G$20,3) -> 2 | E28: =COUNTIFS($F$5:$F$20,2,$G$5:$G$20,4) -> 3 | F28: =COUNTIFS($F$5:$F$20,2,$G$5:$G$20,5) -> 4
A29: 1 | B29: =COUNTIFS($F$5:$F$20,1,$G$5:$G$20,1) -> 0 | C29: =COUNTIFS($F$5:$F$20,1,$G$5:$G$20,2) -> 0 | D29: =COUNTIFS($F$5:$F$20,1,$G$5:$G$20,3) -> 0 | E29: =COUNTIFS($F$5:$F$20,1,$G$5:$G$20,4) -> 0 | F29: =COUNTIFS($F$5:$F$20,1,$G$5:$G$20,5) -> 0
A31: Total de riscos | B31: =COUNTA($C$5:$C$20) -> 16
A32: Riscos críticos abertos (score ≥ 16 e status ≠ Encerrado) | B32: =SUMPRODUCT(($H$5:$H$20>=16)*($N$5:$N$20<>"Encerrado")) -> 1

Sheet GATES PMO
A1: PIQUINZADA 2027 | GATES DE DECISÃO DO PROJETO
A2: Pontos formais de decisão go/no-go ao longo do ciclo de vida do evento.
A4: Gate | B4: Critério | C4: Meta | D4: Resultado atual | E4: Status | F4: Responsável | G4: Prazo | H4: Decisão
A5: GATE 1 — Viabilidade inicial | B5: Cenário Base deve estar classificado como GO ou GO COM RESSALVAS | C5: ≠ NO-GO | D5: =Cenarios!$W$11 -> GO COM RESSALVAS | E5: =IF(D5<>"NO-GO","Atingido","Não atingido") -> Atingido | F5: Diretoria | H5: Pendente
A6: GATE 2 — Contratação da atração principal | B6: Patrocínio contratado (ou garantia financeira equivalente) deve atingir o % mínimo do cachê definido ao lado — não aprovar a contratação definitiva sem isso | C6: =C7*'ENTRADAS PMO'!$D$39 -> 108000 | D6: ='ENTRADAS PMO'!$D$22 -> 60000 | E6: =IF(D6>=C6,"Atingido","Não atingido") -> Não atingido | F6: Comercial | H6: Pendente
B7: ↳ % mínimo de patrocínio/garantia exigido (editável) | C7: 0.6
A8: GATE 3 — Lançamento oficial | B8: Estrutura reservada, licenciamento iniciado e 1º lote de ingressos definido | C8: Sim | D8: Não | E8: =IF(D8="Sim","Atingido",IF(D8="Parcial","Em andamento","Não atingido")) -> Não atingido | F8: Produção | H8: Pendente
A9: GATE 4 — Confirmação operacional | B9: % de vendas realizadas deve atingir a meta mínima definida ao lado, e fornecedores críticos devem estar contratados | C9: =C10 -> 0.7 | D9: =VENDAS!$C$47/'ENTRADAS PMO'!$D$6 -> 0 | E9: =IF(D9>=C9,"Atingido","Não atingido") -> Não atingido | F9: Operações | H9: Pendente
B10: ↳ % mínimo de vendas realizadas exigido (editável) | C10: 0.7
A11: GATE 5 — Liberação final do evento | B11: Licenças emitidas, caixa suficiente para os próximos 30 dias e zero riscos críticos abertos | C11: 0 riscos críticos | D11: =RISCOS!$B$32 -> 1 | E11: =IF(D11=0,"Atingido","Não atingido") -> Não atingido | F11: Direção Geral | H11: Pendente

Sheet FORECAST
A1: PIQUINZADA 2027 | FORECAST PMO (BASELINE = CENÁRIO BASE)
A2: Conforme o evento se aproxima, o forecast substitui os cenários iniciais por uma projeção que combina o realizado com o pipeline em aberto.
A4: Indicador | B4: ORÇAMENTO ORIGINAL | C4: REALIZADO ATÉ O MOMENTO | D4: FORECAST AT COMPLETION
A5: CUSTOS
A6: Custo total | B6: =CUSTOS!$C$52 -> 475795.43 | C6: =CUSTOS!$C$53 -> 0 | D6: =CUSTOS!$C$55 -> 475795.43
A7: ↳ já contratado | C7: =CUSTOS!$C$54 -> 0
A8: ↳ ainda por gastar (ETC) | D8: =CUSTOS!$C$56 -> 475795.43
A10: RECEITAS
A11: Ingressos (pagantes) | B11: =Cenarios!$B$11 -> 2850 | C11: =VENDAS!$C$47 -> 0 | D11: =VENDAS!$C$57 -> 0
A12: Receita de ingressos (líquida) | B12: ='ENTRADAS PMO'!$D$18 -> 278520.8 | C12: =VENDAS!$C$50 -> 0 | D12: =VENDAS!$C$57*'ENTRADAS PMO'!$D$16*(1-'ENTRADAS PMO'!$D$13-'ENTRADAS PMO'!$D$14-'ENTRADAS PMO'!$D$15) -> 0
A13: Receita de consumo/ativações (líquida) | B13: ='ENTRADAS PMO'!$D$33 -> 85505.7 | C13: =VENDAS!$C$47*'ENTRADAS PMO'!$D$30 -> 0 | D13: =VENDAS!$C$57*'ENTRADAS PMO'!$D$30 -> 0
A14: Patrocínio contratado | C14: ='ENTRADAS PMO'!$D$22 -> 60000
A15: Patrocínio pipeline (ponderado) | B15: ='ENTRADAS PMO'!$D$24 -> 127000 | D15: ='ENTRADAS PMO'!$D$24 -> 127000
A16: Outras receitas | B16: ='ENTRADAS PMO'!$D$36 -> 0 | D16: ='ENTRADAS PMO'!$D$36 -> 0
A17: RECEITA TOTAL | B17: =Cenarios!$J$11 -> 491026.5 | C17: =C13+C14+C15 -> 60000 | D17: =D12+D13+D15+D16 -> 127000
A19: RESULTADO
A20: RESULTADO | B20: =B17-B6 -> 15231.069 | C20: =C17-C6 -> 60000 | D20: =D17-D6 -> -348795.43
A21: MARGEM | B21: =IFERROR(B20/B17,0) -> 0.031018833 | C21: =IFERROR(C20/C17,0) -> 1 | D21: =IFERROR(D20/D17,0) -> -2.7464207
A22: Variação do Forecast vs. Orçamento original (R$) | B22: =D20-B20 -> -364026.5

Sheet COMPARATIVO
A1: PIQUINZADA 2027 | COMPARATIVO DOS 3 CENÁRIOS
A2: Todos os valores são links diretos para a aba Cenarios (motor de cálculo) e FLUXO DE CAIXA.
A4: Indicador | B4: CONSERVADOR | C4: BASE | D4: AGRESSIVO
A5: Pagantes | B5: =Cenarios!$B$10 -> 1540 | C5: =Cenarios!$B$11 -> 2850 | D5: =Cenarios!$B$12 -> 3150
A6: % Ocupação | B6: =Cenarios!$D$10 -> 0.75454545 | C6: =Cenarios!$D$11 -> 1 | D6: =Cenarios!$D$12 -> 0.95142857
A7: Ticket médio | B7: =Cenarios!$E$10 -> 80.292208 | C7: =Cenarios!$E$11 -> 106.22456 | D7: =Cenarios!$E$12 -> 111.03175
A8: Receita de ingressos (líq.) | B8: =Cenarios!$F$10 -> 113758 | C8: =Cenarios!$F$11 -> 278520.8 | D8: =Cenarios!$F$12 -> 321770
A9: Receita de consumo/ativações (líq.) | B9: =Cenarios!$G$10 -> 33880 | C9: =Cenarios!$G$11 -> 85505.7 | D9: =Cenarios!$G$12 -> 110250
A10: Patrocínio esperado | B10: =Cenarios!$H$10 -> 47820 | C10: =Cenarios!$H$11 -> 127000 | D10: =Cenarios!$H$12 -> 257400
A11: RECEITA TOTAL | B11: =Cenarios!$J$10 -> 195458 | C11: =Cenarios!$J$11 -> 491026.5 | D11: =Cenarios!$J$12 -> 689420
A12: CUSTO TOTAL | B12: =Cenarios!$K$10 -> 403049.8 | C12: =Cenarios!$K$11 -> 475795.43 | D12: =Cenarios!$K$12 -> 571042.67
A13: RESULTADO | B13: =Cenarios!$L$10 -> -207591.8 | C13: =Cenarios!$L$11 -> 15231.069 | D13: =Cenarios!$L$12 -> 118377.33
A14: MARGEM | B14: =Cenarios!$M$10 -> -1.0620788 | C14: =Cenarios!$M$11 -> 0.031018833 | D14: =Cenarios!$M$12 -> 0.17170568
A15: Break-even (ingressos, com patrocínio) | B15: =Cenarios!$R$10 -> 3705.3733 | C15: =Cenarios!$R$11 -> 2730.7544 | D15: =Cenarios!$R$12 -> 2286.8719
A16: Exposição financeira (Custo Total − Patrocínio contratado) | B16: =Cenarios!$K$10-'ENTRADAS PMO'!$C$22 -> 403049.8 | C16: =Cenarios!$K$11-'ENTRADAS PMO'!$D$22 -> 415795.43 | D16: =Cenarios!$K$12-'ENTRADAS PMO'!$E$22 -> 373042.67
A17: Necessidade de capital de giro | B17: ='FLUXO DE CAIXA'!$B$62 -> 207591.8 | C17: ='FLUXO DE CAIXA'!$B$65 -> 12483.96 | D17: ='FLUXO DE CAIXA'!$B$68 -> 0
A18: Status | B18: =Cenarios!$V$10 -> VERMELHO | C18: =Cenarios!$V$11 -> AMARELO | D18: =Cenarios!$V$12 -> VERDE
A19: Classificação executiva | B19: =Cenarios!$W$10 -> NO-GO | C19: =Cenarios!$W$11 -> GO COM RESSALVAS | D19: =Cenarios!$W$12 -> GO

Sheet SCORE VIABILIDADE
A1: PIQUINZADA 2027 | SCORE DE VIABILIDADE
A2: Índice de 0 a 100. Pesos e metas de referência de cada fator são editáveis. Padrão: cenário Base.
A4: Cenário avaliado | B4: Base
A5: Coluna do cenário (auto) | B5: =IF('SCORE VIABILIDADE'!$B$4="Conservador","C",IF('SCORE VIABILIDADE'!$B$4="Base","D","E")) -> D
A7: Fator | B7: Peso | C7: Meta de referência (100 pts) | D7: Valor atual | E7: Subscore (0-100)
A8: Margem esperada | B8: 0.25 | C8: 0.2 | D8: =INDEX(Cenarios!$M$10:$M$12,MATCH('SCORE VIABILIDADE'!$B$4,Cenarios!$A$10:$A$12,0)) -> 0.031018833 | E8: =MIN(100,MAX(0,D8/C8*100)) -> 15.509416
A9: Margem de segurança (distância do break-even) | B9: 0.2 | C9: 0.25 | D9: =INDEX(Cenarios!$T$10:$T$12,MATCH('SCORE VIABILIDADE'!$B$4,Cenarios!$A$10:$A$12,0)) -> 0.04184055 | E9: =MIN(100,MAX(0,D9/C9*100)) -> 16.73622
A10: Patrocínio contratado / esperado | B10: 0.15 | C10: 1 | D10: =IFERROR(INDIRECT("'ENTRADAS PMO'!"&'SCORE VIABILIDADE'!$B$5&"22")/INDIRECT("'ENTRADAS PMO'!"&'SCORE VIABILIDADE'!$B$5&"24"),1) -> 0.47244094 | E10: =MIN(100,MAX(0,D10/C10*100)) -> 47.244094
A11: Exposição financeira (invertida: 1 − exposição/custo total) | B11: 0.1 | C11: 1 | D11: =1-(INDEX(Cenarios!$K$10:$K$12,MATCH('SCORE VIABILIDADE'!$B$4,Cenarios!$A$10:$A$12,0))-INDIRECT("'ENTRADAS PMO'!"&'SCORE VIABILIDADE'!$B$5&"22"))/INDEX(Cenarios!$K$10:$K$12,MATCH('SCORE VIABILIDADE'!$B$4,Cenarios!$A$10:$A$12,0)) -> 0.12610462 | E11: =MIN(100,MAX(0,D11/C11*100)) -> 12.610462
A12: % de custos já contratados (comprometido/BAC) | B12: 0.1 | C12: 1 | D12: =CUSTOS!$C$54/CUSTOS!$C$52 -> 0 | E12: =MIN(100,MAX(0,D12/C12*100)) -> 0
A13: Contingência ainda disponível | B13: 0.05 | C13: 1 | D13: =IFERROR(1-CUSTOS!H49/CUSTOS!F49,1) -> 1 | E13: =MIN(100,MAX(0,D13/C13*100)) -> 100
A14: Riscos críticos abertos (invertido: cada risco = −25 pts) | B14: 0.1 | C14: 0 | D14: =RISCOS!$B$32 -> 1 | E14: =MAX(0,100-D14*25) -> 75
A15: Necessidade de capital de giro (invertida: 1 − cap.giro/custo total) | B15: 0.05 | C15: 1 | D15: =1-CHOOSE(MATCH('SCORE VIABILIDADE'!$B$4,{"Conservador";"Base";"Agressivo"},0),'FLUXO DE CAIXA'!$B$62,'FLUXO DE CAIXA'!$B$65,'FLUXO DE CAIXA'!$B$68)/INDEX(Cenarios!$K$10:$K$12,MATCH('SCORE VIABILIDADE'!$B$4,Cenarios!$A$10:$A$12,0)) -> 0.97376192 | E15: =MIN(100,MAX(0,D15/C15*100)) -> 97.376192
A17: Soma dos pesos (deve ser 100%) | B17: =SUM(B8:B15) -> 1
A18: SCORE DE VIABILIDADE (0-100) | B18: =SUMPRODUCT(B8:B15,E8:E15) -> 32.941068
A20: FAIXAS DE CLASSIFICAÇÃO (editável)
A21: Classificação | B21: De (score mínimo) | C21: Até (score máximo)
A22: VIÁVEL / GO | B22: 80 | C22: 100
A23: VIÁVEL COM ATENÇÃO | B23: 65 | C23: 79.999
A24: ALTO RISCO / REAVALIAR | B24: 50 | C24: 64.999
A25: NÃO RECOMENDADO / NO-GO | B25: 0 | C25: 49.999
A27: CLASSIFICAÇÃO FINAL | B27: =IF(B18>=80,"VIÁVEL / GO",IF(B18>=65,"VIÁVEL COM ATENÇÃO",IF(B18>=50,"ALTO RISCO / REAVALIAR","NÃO RECOMENDADO / NO-GO"))) -> NÃO RECOMENDADO / NO-GO

Sheet COMO ALIMENTAR
A1: PIQUINZADA 2027 | COMO ALIMENTAR ESTA FERRAMENTA
A3: LEGENDA DE CORES
A4: ● | B4: AZUL (fundo azul claro, texto azul) — Célula de ENTRADA — pode e deve ser editada pelo gestor.
A5: ● | B5: CINZA (fundo cinza, texto preto) — Célula de FÓRMULA/CÁLCULO — não editar; o valor vem de outra célula.
A6: ● | B6: VERDE (texto verde) — LINK para outra aba — mostra de onde vem o dado, mas também não deve ser digitado por cima.
A7: ● | B7: VERDE (fundo verde) — Indicador FAVORÁVEL (dentro da meta).
A8: ● | B8: AMARELO (fundo amarelo) — Indicador de ATENÇÃO (próximo do limite).
A9: ● | B9: VERMELHO (fundo vermelho) — Indicador CRÍTICO (fora da meta, requer ação).
A11: GOVERNANÇA DOS DADOS (SINGLE SOURCE OF TRUTH)
B12: Alimente os dados SOMENTE nestas quatro abas: ENTRADAS PMO (premissas de evento, custos e consumo), VENDAS (lotes de ingresso e vendas realizadas), PATROCINIOS (cotas comerciais e pipeline) e CUSTOS (acompanhamento de fornecedores/pagamentos). Todas as demais abas (Dashboard, Cenarios, ORÇAMENTO x REAL, FLUXO DE CAIXA, BREAK-EVEN, SENSIBILIDADE, COMPARATIVO, SCORE VIABILIDADE, FORECAST) calculam tudo automaticamente a partir dessas quatro. Nunca digite um número por cima de uma célula cinza ou verde.
A14: PASSO A PASSO
B15: Passo 1 — Cenário Conservador: Preencha a coluna "CONSERVADOR" em ENTRADAS PMO, VENDAS e PATROCINIOS com hipóteses prudentes: menor público, menor ticket médio, menor patrocínio (estágios de negociação menos avançados) e custos potencialmente mais elevados. É normal — e até desejável — que este cenário apresente resultado negativo: ele funciona como gatilho de controle de risco para a decisão go/no-go.
B16: Passo 2 — Cenário Base: Preencha a coluna "BASE" com a expectativa mais provável da gestão. Este é o cenário usado como referência em FLUXO DE CAIXA, BREAK-EVEN, SENSIBILIDADE, SCORE DE VIABILIDADE, GATES PMO e FORECAST.
B17: Passo 3 — Cenário Agressivo: Preencha a coluna "AGRESSIVO" com resultados otimistas, porém tecnicamente possíveis e justificáveis (não fantasiosos).
B18: Passo 4 — Atualize os valores reais: Conforme contratos forem assinados, atualize a aba CUSTOS (Fornecedor, Orçamento aprovado, Valor contratado, Valor pago, Status) e a aba PATROCINIOS (mude o Estágio de cada cota para "Contratado" quando fechar).
B19: Passo 5 — Atualize semanalmente vendas e patrocínios: Na aba VENDAS, atualize "Ingressos vendidos até hoje" e a "Data atual"/"Data do evento". Isso recalcula automaticamente velocidade de vendas, projeção de público final, FORECAST e os GATES PMO.
B20: Passo 6 — Analise antes de decidir: Antes de qualquer novo compromisso financeiro relevante (ex.: assinar contrato do artista), consulte nesta ordem: Dashboard (status e recomendação) → GATES PMO (o gate aplicável foi atingido?) → RISCOS (algum risco crítico em aberto?) → FORECAST (o resultado projetado final ainda é saudável?).
A22: MAPA DAS ABAS
B23: Dashboard: Painel executivo com as 3 janelas de cenário, KPIs, indicadores de venda e recomendação PMO.
B24: ENTRADAS PMO: Fonte única das premissas de evento, consumo, atrações, estrutura, operação, marketing, logística e outros custos — por cenário.
B25: VENDAS: Fonte única dos lotes de ingresso por cenário + acompanhamento de vendas realizadas.
B26: PATROCINIOS: Fonte única das cotas comerciais por cenário, com estágio de negociação e probabilidade.
B27: CUSTOS: Registro PMO de custos por item, com BAC/AC/ETC/EAC/VAC (Project Controls / Earned Value adaptado).
B28: Cenarios: Motor de cálculo — não editar. Consolida os 3 cenários e alimenta as demais abas.
B29: ORÇAMENTO x REAL: Comparação orçado x realizado por categoria de custo.
B30: FLUXO DE CAIXA: Entradas e saídas mês a mês (e semana a semana perto do evento), saldo acumulado e necessidade de capital de giro.
B31: BREAK-EVEN: Ponto de equilíbrio por cenário + 4 simuladores "e se?".
B32: SENSIBILIDADE: Impacto de cada variável no resultado, com nível de sensibilidade.
B33: RISCOS: Risk register PMO com mapa de calor Probabilidade × Impacto.
B34: GATES PMO: Pontos formais de decisão go/no-go do projeto.
... B38: Fontes: Referências e notas metodológicas do modelo original.

Sheet Fontes
A1: FONTES E NOTAS DE REFERÊNCIA
A3: Tema | B3: Referência | C3: URL | D3: Uso no modelo
A4: Jammil / referência pública | B4: PNCP — contratação de Jammil para Carnaval 2025 | C4: https://pncp.gov.br/app/contratos?pagina=1&q=jammil&status=todos | D4: Referência de mercado; o arquivo usa R$ 180 mil como premissa editável, não como cotação
A5: Jammil / aderência MG | B5: Prefeitura de Contagem — Pré-Carnaval 2026 com Jammil | C5: https://portal.contagem.mg.gov.br/portal/noticias/0/3/83105/pre-carnaval-de-contagem-tera-banda-jammil-e-tambem-desfiles-dos-blocos | D5: Confirma presença recente da atração na Grande BH
A6: Metodologia | B6: Premissas próprias de planejamento | C6: Modelo interno | D6: Capacidade, preços, custos e patrocínios são hipóteses editáveis e devem ser substituídos por propostas/cotações
